Laboratorios/Lab03Digital1Gar19085/Tabla04POS/POS.v
//Universidad del Valle Digital 1
//Rodrigo José García Ambrosy Carne:19085
//Tabla 04 POS

//Hago el módulo
module POS();

//Variables de entrada y de salida
reg A, B, C, D;
wire w1, w2, w3, w4, w5, w6, w7, w8, w9, w10, w11, w12, w13, Y;

//compuertas

not N1(w1, A);
not N2(w2, B);
not N3(w3, C);
not N4(w4, D);

or O5(w5, A, B, C, w4);
or O6(w6, A, w2, C, D);
or O7(w7, A, w2, C, w4);
or O8(w8, w1, B, C, w4);
or O9(w9, w1, B, w3, w4);
or O10(w10, w1, w2, w3, D);
or O11(w11, w1, w2, C, w4);
or O12(w12, w1, w2, C, D);
or O13(w13, w1, w2, w3, w4);

and A14(Y, w5, w6, w7, w8, w9, w10, w11, w12, w13);

initial begin
    $display("A B C D | Y");   //impresion de la tabla
    $display("---------"); 
    $monitor("%b %b %b %b| %b", A, B, C, D, Y);
    A = 0; B = 0; C = 0; D = 0;
    #1 D = 1;
    #1 C = 1; D = 0;
    #1 D = 1;
    #1 B = 1; C = 0; D = 0;
    #1 D = 1;
    #1 C = 1; D = 0;
    #1 D = 1;
    #1 A = 1; B = 0; C = 0; D = 0;
    #1 D = 1;
    #1 C = 1; D = 0;
    #1 D = 1;
    #1 B = 1; C = 0; D = 0;
    #1 D = 1;
    #1 C = 1; D = 0;
    #1 D = 1;
    #1 $finish;
end

//código que habilita el GTKWave
    initial
        begin
            $dumpfile("POS_tb.vcd");
            $dumpvars(0, POS);
        end

endmodule

Laboratorios/Lab03Digital1Gar19085/Tabla04POS/POS_tb.vcd
$date
	Sat Aug 01 21:28:15 2020
$end
$version
	Icarus Verilog
$end
$timescale
	1ps
$end
$scope module POS $end
$var wire 1 ! Y $end
$var wire 1 " w1 $end
$var wire 1 # w10 $end
$var wire 1 $ w11 $end
$var wire 1 % w12 $end
$var wire 1 & w13 $end
$var wire 1 ' w2 $end
$var wire 1 ( w3 $end
$var wire 1 ) w4 $end
$var wire 1 * w5 $end
$var wire 1 + w6 $end
$var wire 1 , w7 $end
$var wire 1 - w8 $end
$var wire 1 . w9 $end
$var reg 1 / A $end
$var reg 1 0 B $end
$var reg 1 1 C $end
$var reg 1 2 D $end
$upscope $end
$enddefinitions $end
#0
$dumpvars
02
01
00
0/
1.
1-
1,
1+
1*
1)
1(
1'
1&
1%
1$
1#
1"
1!
$end
#1
0!
0*
0)
12
#2
1!
1)
1*
0(
02
11
#3
0)
12
#4
0!
1)
1,
0+
1(
0'
02
01
10
#5
0,
1+
0)
12
#6
1!
1)
1,
0(
02
11
#7
0)
12
#8
1!
1)
1(
1.
1-
1'
0"
02
01
00
1/
#9
0!
0-
0)
12
#10
1!
1)
1-
0(
02
11
#11
0!
0.
0)
12
#12
1)
0%
1$
1(
1.
0'
02
01
10
#13
0$
1%
0)
12
#14
0#
1)
1$
0(
02
11
#15
0&
1#
0)
12
