Laboratorios/Lab06Digital1Gar19085/Ejercicio6/Ejer6.v
//Implementación Ejercicios 1 y 3 


module FFD (input clk, reset, d,
            output reg q);
        always @ (posedge clk or posedge reset)begin
            if (reset) begin
                q <= 1'b0;
            end
            else begin
                q <= d;
            end
        end   
endmodule


//Ejercicio 1

module Ejer1(input A, B, CLK, RESET,
             output Y);
        wire S0, S1, SF0, SF1;

        assign SF0 = (~S1 & ~S0 & A);
        assign SF1 = (S0 & B) | (S1 & A & B);

        FFD F1(CLK, RESET, SF0, S0);
        FFD F2(CLK, RESET, SF1, S1);

        assign Y = (S1 & ~S0 & A & B);

endmodule


//Ejercicio 3

module Ejer3(input A, clk, reset,
             output Y1, Y2, Y3);
    wire S0, S1, S2, SF0, SF1, SF2;

    assign SF0 = (S0 & ~S2 & ~A) | (S0 & S1 & A) | (S0 & ~S1 & S2) | (~S0 & S1 & S2 & ~A) | (~S0 & S1 & ~S2 & ~A);  
    assign SF1 = (S1 & ~S2 & ~A) | (~S1 & ~S2 & A) | (S1 & S2 & A);
    assign SF2 = ~S2;

    FFD F0(clk, reset, SF0, S0);
    FFD F1(clk, reset, SF1, S1);
    FFD F2(clk, reset, SF2, S2);

    assign Y1 = S0; 
    assign Y2 = (S0 & ~S1) | (~S0 & S1);
    assign Y3 = (S1 & ~S2) | (~S1 & S2);

endmodule

Laboratorios/Lab06Digital1Gar19085/Ejercicio6/Ejer6_tb.v
//Testbench de los programas
//TESTBENCH


module testbench();

    reg CLK, reset; 
    reg A, B, A2;
        
        always 
            begin 
                CLK <= 0; reset <= 0; #1 CLK <= 1; #1;
            end

Ejer1 E1(A, B, CLK, reset, Y);
Ejer3 E3(A2, CLK, reset, Y1, Y2, Y3);

  initial begin
        $display("\n");
        $display("Ejercicio 1");
        $display("CLK reset A B Y");
        $monitor("%b %b %b %b %b", CLK, reset, A, B, Y);
           A = 0; B = 0; 
        #1 A = 0; B = 1; 
        #1 A = 1; B = 0;
        #1 A = 1; B = 1;
        #1 A = 0; B = 0;
        #1 A = 0; B = 1;
        #1 A = 1; B = 0;
        #1 A = 1; B = 1;
    end



  initial begin
        $display("\n");
        $display("Ejercicio 3");
        $display("CLK reset A2 Y1 Y2 Y3");
        $monitor("%b %b %b %b %b %b", CLK, reset, A2, Y1, Y2, Y3);
            reset = 1; A2 = 1;
        #8 A2 = 1; reset = 0;
        #2 A2 = 0;
        
    end

    initial 
        #25 $finish;

        initial begin
            $dumpfile("Ejer6_tb.vcd");
            $dumpvars(0, testbench);
        end
endmodule

Laboratorios/Lab06Digital1Gar19085/Ejercicio6/Ejer6_tb.vcd
$date
	Sat Sep 05 06:25:04 2020
$end
$version
	Icarus Verilog
$end
$timescale
	1ps
$end
$scope module testbench $end
$var wire 1 ! Y3 $end
$var wire 1 " Y2 $end
$var wire 1 # Y1 $end
$var wire 1 $ Y $end
$var reg 1 % A $end
$var reg 1 & A2 $end
$var reg 1 ' B $end
$var reg 1 ( CLK $end
$var reg 1 ) reset $end
$scope module E1 $end
$var wire 1 % A $end
$var wire 1 ' B $end
$var wire 1 ( CLK $end
$var wire 1 ) RESET $end
$var wire 1 * SF0 $end
$var wire 1 + SF1 $end
$var wire 1 $ Y $end
$var wire 1 , S1 $end
$var wire 1 - S0 $end
$scope module F1 $end
$var wire 1 ( clk $end
$var wire 1 * d $end
$var wire 1 ) reset $end
$var reg 1 - q $end
$upscope $end
$scope module F2 $end
$var wire 1 ( clk $end
$var wire 1 + d $end
$var wire 1 ) reset $end
$var reg 1 , q $end
$upscope $end
$upscope $end
$scope module E3 $end
$var wire 1 & A $end
$var wire 1 . SF0 $end
$var wire 1 / SF1 $end
$var wire 1 0 SF2 $end
$var wire 1 # Y1 $end
$var wire 1 " Y2 $end
$var wire 1 ! Y3 $end
$var wire 1 ( clk $end
$var wire 1 ) reset $end
$var wire 1 1 S2 $end
$var wire 1 2 S1 $end
$var wire 1 3 S0 $end
$scope module F0 $end
$var wire 1 ( clk $end
$var wire 1 . d $end
$var wire 1 ) reset $end
$var reg 1 3 q $end
$upscope $end
$scope module F1 $end
$var wire 1 ( clk $end
$var wire 1 / d $end
$var wire 1 ) reset $end
$var reg 1 2 q $end
$upscope $end
$scope module F2 $end
$var wire 1 ( clk $end
$var wire 1 0 d $end
$var wire 1 ) reset $end
$var reg 1 1 q $end
$upscope $end
$upscope $end
$upscope $end
$enddefinitions $end
#0
$dumpvars
03
02
01
10
1/
0.
0-
0,
0+
0*
0)
0(
0'
1&
0%
0$
0#
0"
0!
$end
#1
0!
1"
00
11
12
1(
1'
#2
0(
1*
0'
1%
#3
0*
1!
0/
1+
10
1-
01
1(
1'
#4
0(
0+
0'
0%
#5
0"
00
11
02
1,
0-
1(
0+
1'
#6
0(
0'
1%
#7
1/
0!
10
01
1(
1+
1$
1'
#8
0(
#9
0!
1"
00
11
12
1(
#10
0(
1.
0/
0&
#11
1.
10
1#
13
02
01
1(
#12
0(
#13
1!
00
11
1(
#14
0(
#15
1.
0!
10
01
1(
#16
0(
#17
1!
00
11
1(
#18
0(
#19
1.
0!
10
01
1(
#20
0(
#21
1!
00
11
1(
#22
0(
#23
1.
0!
10
01
1(
#24
0(
#25
1!
00
11
1(
