Laboratorios/Lab03Digital1Gar19085/Tabla04SOP/SOP.v
//Universidad del Valle Digital 1
//Rodrigo José García Ambrosy Carne:19085
//Tabla 04 SOP

//Hago el módulo
module SOP();

//Variables de entrada y de salida
reg A, B, C, D;
wire w1, w2, w3, w4, w5, w6, w7, w8, w9, w10, w11, Y;

//compuertas

not N1(w1, A);
not N2(w2, B);
not N3(w3, C);
not N4(w4, D);

and A5(w5, w1, w2, w3, w4);
and A6(w6, w1, w2, C, w4);
and A7(w7, w1, w2, C, D);
and A8(w8, w1, B, C, w4);
and A9(w9, w1, B, C, D);
and A10(w10, A, w2, w3, w4);
and A11(w11, A, w2, C, w4);

or O12(Y, w5, w6, w7, w8, w9, w10, w11);

initial begin
    $display("A B C D | Y");   //impresion de la tabla
    $display("-----------"); 
    $monitor("%b %b %b %b | %b", A, B, C, D, Y);
    A = 0; B = 0; C = 0; D = 0;
    #1 D = 1;
    #1 C = 1; D = 0;
    #1 D = 1;
    #1 B = 1; C = 0; D = 0;
    #1 D = 1;
    #1 C = 1; D = 0;
    #1 D = 1;
    #1 A = 1; B = 0; C = 0; D = 0;
    #1 D = 1;
    #1 C = 1; D = 0;
    #1 D = 1;
    #1 B = 1; C = 0; D = 0;
    #1 D = 1;
    #1 C = 1; D = 0;
    #1 D = 1;
    #1 $finish;
end

//código que habilita el GTKWave
    initial
        begin
            $dumpfile("SOP_tb.vcd");
            $dumpvars(0, SOP);
        end

endmodule

Laboratorios/Lab03Digital1Gar19085/Tabla04SOP/SOP_tb.vcd
$date
	Sat Aug 01 21:30:24 2020
$end
$version
	Icarus Verilog
$end
$timescale
	1ps
$end
$scope module SOP $end
$var wire 1 ! Y $end
$var wire 1 " w1 $end
$var wire 1 # w10 $end
$var wire 1 $ w11 $end
$var wire 1 % w2 $end
$var wire 1 & w3 $end
$var wire 1 ' w4 $end
$var wire 1 ( w5 $end
$var wire 1 ) w6 $end
$var wire 1 * w7 $end
$var wire 1 + w8 $end
$var wire 1 , w9 $end
$var reg 1 - A $end
$var reg 1 . B $end
$var reg 1 / C $end
$var reg 1 0 D $end
$upscope $end
$enddefinitions $end
#0
$dumpvars
00
0/
0.
0-
0,
0+
0*
0)
1(
1'
1&
1%
0$
0#
1"
1!
$end
#1
0!
0(
0'
10
#2
1!
1)
1'
0&
00
1/
#3
0)
1*
0'
10
#4
0!
1'
0*
1&
0%
00
0/
1.
#5
0'
10
#6
1!
1+
1'
0&
00
1/
#7
0+
1,
0'
10
#8
1#
1'
1&
0,
1%
0"
00
0/
0.
1-
#9
0!
0#
0'
10
#10
1!
1$
1'
0&
00
1/
#11
0!
0$
0'
10
#12
1'
1&
0%
00
0/
1.
#13
0'
10
#14
1'
0&
00
1/
#15
0'
10
