Proyecto Digital/Galaga.v
//UNIVERSIDAD DEL VALLE DE GUATEMALA
//RODRIGO JOSÉ GARCÍA AMBROSY

//FLIP-FLOP D
module FFD (input CLK, RST, D,
            output reg Q);
        always @ (posedge CLK or posedge RST)begin
            if (RST)
                Q <= 1'b0;
            else
                Q <= D;
        end   
endmodule

//ECUACIONES FSM DE LA NAVE 1
module FSMN1 (input wire LEFT, RIGHT, CLK, RST,
            output L, C, R);
    wire SB1, SB0, SBF1, SBF0;

    assign L = (SB0 & LEFT)  | (SB0 & ~RIGHT) | (~SB1 & LEFT & ~RIGHT);
    assign C = (SB0 & ~LEFT & RIGHT) | (SB1 & LEFT & ~RIGHT) | (~SB1 & ~SB0 & LEFT & RIGHT) | (~SB1 & ~SB0 & ~LEFT & ~RIGHT);
    assign R = (SB1 & ~LEFT) | (SB1 & RIGHT) | (~SB0 & ~LEFT & RIGHT);
    assign SBF1 = (SB1 & ~LEFT) | (SB1 & RIGHT) | (~SB0 & ~LEFT & RIGHT);
    assign SBF0 = (SB0 & LEFT) | (SB0 & ~RIGHT) | (~SB1 & LEFT & ~RIGHT); 

    FFD JuI(CLK, RST, SBF0, SB0);
    FFD JuII(CLK, RST, SBF1, SB1);

endmodule

//ECUACIONES FSM DE LA NAVE 2
module FSMN2 (input wire LEFT2, RIGHT2, CLK, RST,
            output L2, C2, R2);
        wire SB4, SB2, SBF4, SBF2;    
    assign L2 = (SB2 & LEFT2)  | (SB2 & ~RIGHT2) | (~SB4 & LEFT2 & ~RIGHT2);
    assign C2 = (SB2 & ~LEFT2 & RIGHT2) | (SB4 & LEFT2 & ~RIGHT2) | (~SB4 & ~SB2 & LEFT2 & RIGHT2) | (~SB4 & ~SB2 & ~LEFT2 & ~RIGHT2);
    assign R2 = (SB4 & ~LEFT2)  | (SB4 & RIGHT2) | (~SB2 & ~LEFT2 & RIGHT2);
    assign SBF4 = (SB4 & ~LEFT2)  | (SB4 & RIGHT2) | (~SB2 & ~LEFT2 & RIGHT2);
    assign SBF2 = (SB2 & LEFT2)  | (SB2 & ~RIGHT2) | (~SB4 & LEFT2 & ~RIGHT2); 

    FFD Ju3(CLK, RST, SBF4, SB4);
    FFD Ju4(CLK, RST, SBF2, SB2);

endmodule

//ECUACIONES SECCIÓN DE PPOSICIÓN
module posicion(input wire L, C, R, L2, C2, R2, output MP);

    assign MP = (~L & ~C & R & ~L2 & ~C2 & R2) | (~L & C & ~R & ~L2 & C2 & ~R2) | (L & ~C & ~R & L2 & ~C2 & ~R2);            

endmodule

//ECUACIONES FSM ARMADURA
module Armor(input wire M, MP1, MP2, CLK, RST,
            output wire A2, A1);
        wire SA2, SA1, SAF2, SAF1;     

    assign SAF2 = (SA2)  | (M & MP1 & ~MP2);
    assign SAF1 = (SA1) | (M & ~MP1 & MP2);
    assign A2 = (SA1) | (M & ~MP1 & MP2);
    assign A1 = (SA2)  | (M & MP1 & ~MP2);

    FFD Ju6(CLK, RST, SAF1, SA1);
    FFD Ju7(CLK, RST, SAF2, SA2);

endmodule

//ECUACIONES FSM JUEGO
module juego(input wire M, DP1, DP2, A2, A1, CLK, RST,
            output wire P1A, P1B, P1C, P2A, P2B, P2C, DONE);
        wire  SJ3, SJ2, SJ1, SJ0, SJF3, SJF2, SJF1, SJF0;  

    assign SJF3 = (SJ3 & ~M)  | (SJ3 & DP1)  | (SJ3 & ~DP2)  | (SJ3 & ~A1)  | (SJ2 & M & ~DP1 & DP2 & A1) | (~SJ2 & SJ1 & SJ0 & M & DP1 & ~DP2 & A2) | (SJ2 & ~SJ1 & SJ0 & M & DP1 & ~DP2 & A2) | (SJ2 & SJ1 & ~SJ0 & M & DP1 & ~DP2 & A2);
    assign SJF2 = (SJ2 & SJ1)  | (SJ2 & ~M)  | (SJ2 & DP1 & DP2)  | (SJ2 & ~DP1 & ~DP2) | (SJ3 & M & ~DP1 & DP2 & A1) | (~SJ2 & SJ0 & M & ~DP1 & DP2 & A1) | (SJ1 & ~SJ0 & M & DP1 & ~DP2 & A2) | (SJ2 & ~SJ0 & ~DP2) | (SJ2 & DP2 & ~A1) | (SJ2 & ~DP2 & ~A2);
    assign SJF1 = (SJ1 & ~M) | (SJ3 & M & ~DP1 & DP2 & A1) | (SJ3 & M & DP1 & ~DP2 & A1) | (~SJ3 & ~SJ1 & M & DP1 & ~DP2 & A2) | (~SJ2 & SJ1 & ~DP1) | (SJ1 & ~SJ0 & ~DP1) | (SJ1 & DP1 & DP2) | (SJ1 & ~DP2 & ~A2) | (SJ2 & SJ1 & SJ0 & ~DP2) | (SJ2 & SJ1 & SJ0 & ~A1);
    assign SJF0 = (SJ0 & ~M) | (SJ0 & DP1 & DP2) | (SJ0 & ~DP1 & ~DP2) | (SJ3 & M & DP1 & ~DP2 & A1) | (~SJ2 & SJ1 & ~SJ0 & M & DP1 & ~DP2 & A2) | (SJ2 & ~SJ1 & ~SJ0 & M & DP1 & ~DP2 & A2) | (SJ1 & SJ0 & DP2) | (SJ0 & DP2 & ~A1) | (SJ0 & ~DP2 & ~A2) | (~SJ2 & ~SJ1 & SJ0 & ~DP2) | (~SJ3 & ~SJ2 & ~SJ0 & M & ~DP1 & DP2 & A1) | (~SJ3 & ~SJ1 & ~SJ0 & M & ~DP1 & DP2 & A1);
    assign P1A = (SJ3)  | (~SJ2 & SJ0)  | (SJ2 & ~SJ0)  | (M & ~DP1 & DP2 & A1) | (SJ1 & SJ0);
    assign P1B = (SJ2 & SJ1) | (SJ2 & ~SJ0) | (SJ3 & M & ~DP1 & DP2 & A1) | (~SJ2 & SJ0 & M & ~DP1 & DP2 & A1);
    assign P1C = (SJ2 & SJ1 & M & ~DP1 & DP2 & A1) | (SJ2 & ~SJ0 & M & ~DP1 & DP2 & A1);
    assign P2A = (SJ3) | (SJ1) | (SJ2 & SJ0) | (M & DP1 & ~DP2 & A2);
    assign P2B = (SJ3) | (SJ2 & ~SJ1 & SJ0) | (SJ2 & SJ1 & ~SJ0) | (SJ1 & M & DP1 & ~DP2 & A2);
    assign P2C = (SJ3 & M & DP1 & ~DP2 & A1) | (SJ2 & ~SJ1 & SJ0 & M & DP1 & ~DP2 & A2) | (SJ2 & SJ1 & ~SJ0 & M & DP1 & ~DP2 & A2);
    assign DONE = (SJ3 & M & DP1 & ~DP2 & A1)  | (SJ2 & SJ1 & M & ~DP1 & DP2 & A1) | (SJ2 & ~SJ0 & M & ~DP1 & DP2 & A1) | (SJ2 & ~SJ1 & SJ0 & M & DP1 & ~DP2 & A2)| (SJ2 & SJ1 & ~SJ0 & M & DP1 & ~DP2 & A2);

    FFD Ju8(CLK, RST, SJF0, SJ0);
    FFD Ju9(CLK, RST, SJF1, SJ1);
    FFD Ju10(CLK, RST, SJF2, SJ2);
    FFD Ju11(CLK, RST, SJF3, SJ3);

endmodule


module GALAGA(input wire LEFT, RIGHT, LEFT2, RIGHT2, DP1, DP2, CLK, RST, 
                output P1A, P1B, P1C, P2A, P2B, P2C, DONE);
        wire L, C, R, L2, C2, R2, M, A1, A2;

        FSMN1       J1(LEFT, RIGHT, CLK, RST, L, C, R);
        FSMN2       J2(LEFT2, RIGHT2, CLK, RST, L2, C2, R2);
        posicion    POS3(L, C, R, L2, C2, R2, M);
        Armor       AR(M, DP1, DP2,  CLK, RST, A2, A1);
        juego       GAL(M, DP1, DP2, A2, A1, CLK, RST, P1A, P1B, P1C, P2A, P2B, P2C, DONE);
endmodule

Proyecto Digital/Galaga_tb.v


module testbench();
    //ENTRADAS Y SALIDAS FSM NAVE 1
    reg CLK, RST; 
    reg LEFT, RIGHT;
    reg LEFT2, RIGHT2;
    reg DP1, DP2;
    wire L, C, R; 
    wire L2, C2, R2;
    wire MP;  
    wire P1A, P1B, P1C, P2A, P2B, P2C, DONE;

        always 
            begin 
                CLK <= 0; RST <= 0; #1 CLK <= 1; #1;
            end

        GALAGA retro(LEFT, RIGHT, LEFT2, RIGHT2, DP1, DP2, CLK, RST, P1A, P1B, P1C, P2A, P2B, P2C, DONE);


  initial begin
        $display("\n");
        $display("inicio");
    end
  
  initial begin
        $display("\n");
        $display("posicion");
        $display("CLK |RST | LEFT RIGHT | LEFT2 RIGHT2  DP1 DP2 | P1A P1B P1C | P2A P2B P2C | DONE");
        $monitor("%b  | %b   |  %b     %b  |  %b   %b  |  %b  %b  |  %b  %b  %b  |  %b  %b  %b  | %b", 
        CLK, RST, LEFT, RIGHT, LEFT2, RIGHT2,DP1, DP2, P1A, P1B, P1C, P2A, P2B, P2C, DONE);
        CLK = 0; RST = 0; LEFT = 0; RIGHT = 0; LEFT2 = 0; RIGHT2 = 0;  DP1 = 0; DP2 = 0;
        #1 RST = 1; LEFT = 0; RIGHT = 0; LEFT2 = 0; RIGHT2 = 0;  DP1 = 0; DP2 = 0;
        #1 RST = 0; LEFT = 0; RIGHT = 0; LEFT2 = 0; RIGHT2 = 0;  DP1 = 0; DP2 = 0;
        #1 LEFT = 1; RIGHT = 0; LEFT2 = 0; RIGHT2 = 1; DP1 = 0; DP2 = 0;
        #1 LEFT = 0; RIGHT = 0; LEFT2 = 1; RIGHT2 = 0; DP1 = 0; DP2 = 1;
        #1 LEFT = 0; RIGHT = 1; LEFT2 = 0; RIGHT2 = 0; DP1 = 1; DP2 = 0;
        #1 LEFT = 0; RIGHT = 0; LEFT2 = 1; RIGHT2 = 0; DP1 = 1; DP2 = 0;
        #1 LEFT = 0; RIGHT = 0; LEFT2 = 0; RIGHT2 = 0; DP1 = 0; DP2 = 1;
        #1 LEFT = 0; RIGHT = 0; LEFT2 = 0; RIGHT2 = 1; DP1 = 0; DP2 = 0; 
        #1 LEFT = 0; RIGHT = 1; LEFT2 = 0; RIGHT2 = 0; DP1 = 0; DP2 = 1;   
        #1 LEFT = 0; RIGHT = 0; LEFT2 = 0; RIGHT2 = 0; DP1 = 0; DP2 = 1;
        #1 LEFT = 0; RIGHT = 0; LEFT2 = 0; RIGHT2 = 0; DP1 = 1; DP2 = 0;
        #1 LEFT = 0; RIGHT = 0; LEFT2 = 0; RIGHT2 = 0; DP1 = 0; DP2 = 0;
        #1 LEFT = 0; RIGHT = 0; LEFT2 = 0; RIGHT2 = 0; DP1 = 1; DP2 = 0;
        #1 LEFT = 0; RIGHT = 0; LEFT2 = 0; RIGHT2 = 0; DP1 = 1; DP2 = 0;
        #1 LEFT = 0; RIGHT = 0; LEFT2 = 0; RIGHT2 = 0; DP1 = 1; DP2 = 0;
        
  end

    always 
        #1 CLK = ~CLK;

    initial 
        #18 $finish;

        initial begin
            $dumpfile("Galaga_tb.vcd");
            $dumpvars(0, testbench);
        end
endmodule

Proyecto Digital/Galaga_tb.vcd
$date
	Sun Oct 11 18:51:05 2020
$end
$version
	Icarus Verilog
$end
$timescale
	1ps
$end
$scope module testbench $end
$var wire 1 ! P2C $end
$var wire 1 " P2B $end
$var wire 1 # P2A $end
$var wire 1 $ P1C $end
$var wire 1 % P1B $end
$var wire 1 & P1A $end
$var wire 1 ' DONE $end
$var reg 1 ( CLK $end
$var reg 1 ) DP1 $end
$var reg 1 * DP2 $end
$var reg 1 + LEFT $end
$var reg 1 , LEFT2 $end
$var reg 1 - RIGHT $end
$var reg 1 . RIGHT2 $end
$var reg 1 / RST $end
$scope module retro $end
$var wire 1 ( CLK $end
$var wire 1 ) DP1 $end
$var wire 1 * DP2 $end
$var wire 1 + LEFT $end
$var wire 1 , LEFT2 $end
$var wire 1 - RIGHT $end
$var wire 1 . RIGHT2 $end
$var wire 1 / RST $end
$var wire 1 0 R2 $end
$var wire 1 1 R $end
$var wire 1 ! P2C $end
$var wire 1 " P2B $end
$var wire 1 # P2A $end
$var wire 1 $ P1C $end
$var wire 1 % P1B $end
$var wire 1 & P1A $end
$var wire 1 2 M $end
$var wire 1 3 L2 $end
$var wire 1 4 L $end
$var wire 1 ' DONE $end
$var wire 1 5 C2 $end
$var wire 1 6 C $end
$var wire 1 7 A2 $end
$var wire 1 8 A1 $end
$scope module AR $end
$var wire 1 8 A1 $end
$var wire 1 7 A2 $end
$var wire 1 ( CLK $end
$var wire 1 ) MP1 $end
$var wire 1 * MP2 $end
$var wire 1 / RST $end
$var wire 1 9 SAF1 $end
$var wire 1 : SAF2 $end
$var wire 1 ; SA2 $end
$var wire 1 < SA1 $end
$var wire 1 2 M $end
$scope module Ju6 $end
$var wire 1 ( CLK $end
$var wire 1 9 D $end
$var wire 1 / RST $end
$var reg 1 < Q $end
$upscope $end
$scope module Ju7 $end
$var wire 1 ( CLK $end
$var wire 1 : D $end
$var wire 1 / RST $end
$var reg 1 ; Q $end
$upscope $end
$upscope $end
$scope module GAL $end
$var wire 1 8 A1 $end
$var wire 1 7 A2 $end
$var wire 1 ( CLK $end
$var wire 1 ' DONE $end
$var wire 1 ) DP1 $end
$var wire 1 * DP2 $end
$var wire 1 & P1A $end
$var wire 1 % P1B $end
$var wire 1 $ P1C $end
$var wire 1 # P2A $end
$var wire 1 " P2B $end
$var wire 1 ! P2C $end
$var wire 1 / RST $end
$var wire 1 = SJF0 $end
$var wire 1 > SJF1 $end
$var wire 1 ? SJF2 $end
$var wire 1 @ SJF3 $end
$var wire 1 A SJ3 $end
$var wire 1 B SJ2 $end
$var wire 1 C SJ1 $end
$var wire 1 D SJ0 $end
$var wire 1 2 M $end
$scope module Ju10 $end
$var wire 1 ( CLK $end
$var wire 1 ? D $end
$var wire 1 / RST $end
$var reg 1 B Q $end
$upscope $end
$scope module Ju11 $end
$var wire 1 ( CLK $end
$var wire 1 @ D $end
$var wire 1 / RST $end
$var reg 1 A Q $end
$upscope $end
$scope module Ju8 $end
$var wire 1 ( CLK $end
$var wire 1 = D $end
$var wire 1 / RST $end
$var reg 1 D Q $end
$upscope $end
$scope module Ju9 $end
$var wire 1 ( CLK $end
$var wire 1 > D $end
$var wire 1 / RST $end
$var reg 1 C Q $end
$upscope $end
$upscope $end
$scope module J1 $end
$var wire 1 6 C $end
$var wire 1 ( CLK $end
$var wire 1 4 L $end
$var wire 1 + LEFT $end
$var wire 1 1 R $end
$var wire 1 - RIGHT $end
$var wire 1 / RST $end
$var wire 1 E SBF0 $end
$var wire 1 F SBF1 $end
$var wire 1 G SB1 $end
$var wire 1 H SB0 $end
$scope module JuI $end
$var wire 1 ( CLK $end
$var wire 1 E D $end
$var wire 1 / RST $end
$var reg 1 H Q $end
$upscope $end
$scope module JuII $end
$var wire 1 ( CLK $end
$var wire 1 F D $end
$var wire 1 / RST $end
$var reg 1 G Q $end
$upscope $end
$upscope $end
$scope module J2 $end
$var wire 1 5 C2 $end
$var wire 1 ( CLK $end
$var wire 1 3 L2 $end
$var wire 1 , LEFT2 $end
$var wire 1 0 R2 $end
$var wire 1 . RIGHT2 $end
$var wire 1 / RST $end
$var wire 1 I SBF2 $end
$var wire 1 J SBF4 $end
$var wire 1 K SB4 $end
$var wire 1 L SB2 $end
$scope module Ju3 $end
$var wire 1 ( CLK $end
$var wire 1 J D $end
$var wire 1 / RST $end
$var reg 1 K Q $end
$upscope $end
$scope module Ju4 $end
$var wire 1 ( CLK $end
$var wire 1 I D $end
$var wire 1 / RST $end
$var reg 1 L Q $end
$upscope $end
$upscope $end
$scope module POS3 $end
$var wire 1 6 C $end
$var wire 1 5 C2 $end
$var wire 1 4 L $end
$var wire 1 3 L2 $end
$var wire 1 2 MP $end
$var wire 1 1 R $end
$var wire 1 0 R2 $end
$upscope $end
$upscope $end
$upscope $end
$enddefinitions $end
#0
$dumpvars
xL
xK
xJ
xI
xH
xG
xF
xE
xD
xC
xB
xA
x@
x?
x>
x=
x<
x;
x:
x9
x8
x7
x6
x5
x4
x3
x2
x1
x0
0/
0.
0-
0,
0+
0*
0)
0(
0'
x&
x%
0$
x#
x"
0!
$end
#1
0=
12
0>
0?
0@
16
15
0&
0"
0%
0E
04
0F
01
0J
00
0I
03
0#
07
09
08
0:
0H
0G
0K
0L
0<
0;
0D
0C
0B
0A
1(
1/
#2
0(
0/
#3
02
06
05
14
1E
10
1J
1(
1.
1+
#4
07
09
02
16
13
1I
04
0E
00
0J
0(
1*
0.
1,
0+
#5
1L
05
13
1I
06
11
1F
1(
0*
1)
0,
1-
#6
16
01
0F
0(
1,
0-
#7
1(
1*
0)
0,
#8
12
03
15
0I
0(
0*
1.
#9
0L
02
03
15
0I
06
09
07
11
1F
1(
1*
0.
1-
#10
17
19
12
16
01
0F
0(
0-
#11
1>
1#
1<
1:
18
19
17
1(
0*
1)
#12
0>
0#
0:
08
0(
0)
#13
1>
1#
1:
18
1(
1)
#14
0(
#15
1=
0>
1?
1"
1C
1;
1(
#16
0(
#17
0=
1>
1'
1!
0?
1@
0%
0&
1D
0C
1B
1(
