Laboratorios/Lab05Digital1Gar19085/Ejercicio4/Mux.v
//Universidad del Valle de Guatemala
//Digital 1
//Laboratorio 05
//Rodrigo José García Ambrosy. Carnet: 19085

//IMPLEMENTO DEL MODULO MUX2:1 UTILIZADO EL OPERADOR TERNARIO
module Mux2x1(input wire [3:0] D0, D1, 
              input wire      S,
              output wire [3:0] Y);
    
    assign Y = S ? D1 : D0;

endmodule //CIERRO MODULO

//IMPLEMENTACIÓN DE MUX4:1 CON MUX2:1
module Mux4x1(input wire [3:0]  D0, D1, D2, D3,
              input wire [1:0]  S1,
              output wire [3:0] Y);

    wire [3:0] low, hig;

    Mux2x1 lowmux(D0, D1, S1[0], low);
    Mux2x1 higmux(D2, D3, S1[0], high);
    Mux2x1 outmux(low, high, S1[1], Y);

endmodule //CIERRO MODULO


//IMPLEMENTACIÓN DE MUX8:1 CON MUX4:1
module Mux8x1(input wire [3:0] D0, D1, D2, D3, D4, D5, D6, D7, D8,
              input wire [1:0] S2,
              output wire [3:0] Y);

        wire [3:0] SA, SB;
    
    Mux4x1 lomux(D0, D1, D2, D3, S2[0], SA);
    Mux4x1 himux(D4, D5, D6, D7, S2[0], SB); 
    Mux2x1 finalmux(SA, SB, S2[0], Y);
    

endmodule //CIERRO MODULO


//IMPLEMENTO TABLA1 DEL MUX2:1
    module M2x1Tabla01( input wire [1:0] B, C,
                        input wire   A, 
                        output wire [1:0] Y);

        Mux2x1  M1(A, B, C, Y);

    endmodule 


//IMPLEMENTO TABLA1 DEL MUX4:1
    module M4x1Tabla01();

    endmodule


//IMPLEMENTO TABLA1 DEL MUX8:1
    module M8x1Tabla01();

    endmodule


//IMPLEMENTO TABLA 2 DEL MUX2:1
    module M2x1Tabla02( input wire [1:0] B, C,
                        input wire   A, 
                        output wire [1:0] Y);

        Mux2x1  M1(A, B, C, Y);

    endmodule 


//IMPLEMENTO TABLA2 DEL MUX4:1
    module M4x1Tabla02();

    endmodule


//IMPLEMENTO TABLA2 DEL MUX8:1
    module M8x1Tabla02();

    endmodule

Laboratorios/Lab05Digital1Gar19085/Ejercicio4/Mux_tb.v
//LAB 04
//RODRIGO GARCÍA 19085


//CONFIG DEL TESTBENCH

module  TESTBENCH();
    //MUX 2:1
    reg t1, t2, t3; //TABLA 01
    wire PzI;

    //MUX 4:1

//MUX 2:1
    M2x1Tabla01 M2(t1, t2, t3, PzI);


    initial begin
        $display("MUX2:1");
        $display("A B C | Y");
        $display("------|---");
        $monitor("%b %b %b | %b", t1, t2, t3, PzI);
           t1 = 0; t2 = 0; t3 = 0;
        #1 t1 = 0; t2 = 0; t3 = 1;
        #1 t1 = 0; t2 = 1; t3 = 0;
        #1 t1 = 0; t2 = 1; t3 = 1;
        #1 t1 = 1; t2 = 0; t3 = 0;
        #1 t1 = 1; t2 = 0; t3 = 1;
        #1 t1 = 1; t2 = 1; t3 = 0;
        #1 t1 = 1; t2 = 1; t3 = 1;
    end //Termina en 8


//TESTBENCH MUX2:1
    initial 
        #9 $finish;

    initial begin  
        $dumpfile("Mux_tb.vcd");
        $dumpvars(0, TESTBENCH);
    end 

endmodule

Laboratorios/Lab05Digital1Gar19085/Ejercicio4/Mux_tb.vcd
$date
	Sat Aug 15 13:33:49 2020
$end
$version
	Icarus Verilog
$end
$timescale
	1ps
$end
$scope module TESTBENCH $end
$var wire 1 ! PzI $end
$var reg 1 " t1 $end
$var reg 1 # t2 $end
$var reg 1 $ t3 $end
$scope module M2 $end
$var wire 1 $ A $end
$var wire 2 % B [1:0] $end
$var wire 2 & C [1:0] $end
$var wire 2 ' Y [1:0] $end
$scope module M1 $end
$var wire 4 ( D0 [3:0] $end
$var wire 4 ) D1 [3:0] $end
$var wire 1 * S $end
$var wire 4 + Y [3:0] $end
$upscope $end
$upscope $end
$upscope $end
$enddefinitions $end
#0
$dumpvars
b0 +
0*
b0 )
b0 (
b0 '
b0 &
b0 %
0$
0#
0"
0!
$end
#1
1!
b1 '
b1 +
b1 (
1$
#2
0!
b0 '
b0 +
1*
b0 (
0$
b1 &
1#
#3
b1 (
1$
#4
0!
b0 '
0*
b0 +
b0 (
0$
b0 &
0#
b1 )
b1 %
1"
#5
1!
b1 '
b1 +
b1 (
1$
#6
1*
b0 (
0$
b1 &
1#
#7
b1 (
1$
