Laboratorios/Lab10Digital1Gar19085/Ejercicio01/PRF.v
/*
Rodrigo García
Lab10
*/

//FlipFLops Para el Fetch
module FFD1 (input CLK, RST, ENABLE, D,
            output reg Q);
        always @ (posedge CLK or posedge RST)begin
            if (RST) begin
                Q <= 1'b0;
            end
            else if (ENABLE) begin
                Q <= D;
            end
        end   
endmodule


module FFD4 (input CLK, RST, ENABLE, input [3:0] D, 
            output wire [3:0]Q);
        FFD1 F4F1(CLK, RST, ENABLE,  D[3], Q[3]);
        FFD1 F4F2(CLK, RST, ENABLE, D[2], Q[2]);
        FFD1 F4F3(CLK, RST, ENABLE,  D[1], Q[1]);
        FFD1 F4F4(CLK, RST, ENABLE, D[0], Q[0]);
endmodule    

//Fetch
module FFD8(input CLK, RST, ENABLE, input [7:0] D, 
            output wire [3:0]Q1,
            output wire [3:0]Q2);
        FFD4 Ju87(CLK, RST, ENABLE,  D[3:0], Q1[3:0]);
        FFD4 Ju88(CLK, RST, ENABLE,  D[3:0], Q2[3:0]);

endmodule            


module Counter(RST, CLK, ENABLE, LOAD, E, COUNT);
input RST, CLK, ENABLE, LOAD;
input wire [11:0] E;
output [11:0] COUNT;
reg [11:0] COUNT;

always @ (posedge CLK or posedge RST)
    if (LOAD) begin
        COUNT <= E;
    end
    else if  (ENABLE) begin
        if (~LOAD);
        COUNT <= COUNT + 1;
    end 
    else if (RST) begin
        COUNT <= 0;   
    end
endmodule



module  ROM4Kx8(address, Dout);
    input   [11:0] address;
    output  [7:0] Dout;
    
    assign Dout = memory[address];
    reg [7:0]   memory[0:4095];

    initial begin
        $readmemh("memory.list", memory);
    end

endmodule    



module MAIN(input CLK, RST, ENABLE1, ENABLE2, LOAD, input [11:0] IN,
            output [3:0] Q1, Q2);
    wire [11:0]COUNTADD;
    wire [7:0]DIN;

    Counter PzI(CLK, RST, ENABLE1, LOAD, IN, COUNTADD);
    ROM4Kx8 PZII(COUNTADD, DIN);
    FFD8    PzIII(CLK, RST, ENABLE2, DIN, Q1, Q2);

endmodule

Laboratorios/Lab10Digital1Gar19085/Ejercicio01/PRF_tb.v



module testbench();

reg CLK, RST, ENABLE1, ENABLE2, LOAD; 
reg [11:0]IN;
wire [3:0] Q1;
wire [3:0] Q2;


    MAIN T1(CLK, RST, ENABLE1, ENABLE2, LOAD, IN, Q1, Q2);

        always 
            begin 
                CLK <= 0; RST <= 0; #1 CLK <= 1; #1;
            end

initial begin
        $display("\n");
        $display("EJERCICIO 01");
        $display("CLK| RST | ENABLE1 | ENABLE2 | LOAD | IN | Q1 | Q2 | Q1Hex | Q2Hex |");
        $monitor("%b |  %b |   %b    |   %b    |  %b  | %b | %b | %b |  %h   |   %h  |",
        CLK, RST, ENABLE1, ENABLE2, LOAD, IN, Q1, Q2, Q1, Q2);
        CLK = 0; RST = 0; ENABLE1 = 0; ENABLE2 = 0; LOAD = 0; IN = 0; 
        #1 RST = 1;
        #1 RST = 0;
        #1 ENABLE1 = 1;
        #1 ENABLE2 = 1;
        #1 IN = 12'b00000001;
end
  
   always
    #5  CLK = ~CLK;
  
   initial 
        #60 $finish;


        initial begin
            $dumpfile("PRF_tb.vcd");
            $dumpvars(0, testbench);
        end

endmodule

Laboratorios/Lab10Digital1Gar19085/Ejercicio01/PRF_tb.vcd
$date
	Thu Nov 05 17:12:45 2020
$end
$version
	Icarus Verilog
$end
$timescale
	1ps
$end
$scope module testbench $end
$var wire 4 ! Q2 [3:0] $end
$var wire 4 " Q1 [3:0] $end
$var reg 1 # CLK $end
$var reg 1 $ ENABLE1 $end
$var reg 1 % ENABLE2 $end
$var reg 12 & IN [11:0] $end
$var reg 1 ' LOAD $end
$var reg 1 ( RST $end
$scope module T1 $end
$var wire 1 # CLK $end
$var wire 1 $ ENABLE1 $end
$var wire 1 % ENABLE2 $end
$var wire 12 ) IN [11:0] $end
$var wire 1 ' LOAD $end
$var wire 1 ( RST $end
$var wire 4 * Q2 [3:0] $end
$var wire 4 + Q1 [3:0] $end
$var wire 8 , DIN [7:0] $end
$var wire 12 - COUNTADD [11:0] $end
$scope module PZII $end
$var wire 8 . Dout [7:0] $end
$var wire 12 / address [11:0] $end
$upscope $end
$scope module PzI $end
$var wire 1 ( CLK $end
$var wire 12 0 E [11:0] $end
$var wire 1 $ ENABLE $end
$var wire 1 ' LOAD $end
$var wire 1 # RST $end
$var reg 12 1 COUNT [11:0] $end
$upscope $end
$scope module PzIII $end
$var wire 1 # CLK $end
$var wire 8 2 D [7:0] $end
$var wire 1 % ENABLE $end
$var wire 1 ( RST $end
$var wire 4 3 Q2 [3:0] $end
$var wire 4 4 Q1 [3:0] $end
$scope module Ju87 $end
$var wire 1 # CLK $end
$var wire 4 5 D [3:0] $end
$var wire 1 % ENABLE $end
$var wire 1 ( RST $end
$var wire 4 6 Q [3:0] $end
$scope module F4F1 $end
$var wire 1 # CLK $end
$var wire 1 7 D $end
$var wire 1 % ENABLE $end
$var wire 1 ( RST $end
$var reg 1 8 Q $end
$upscope $end
$scope module F4F2 $end
$var wire 1 # CLK $end
$var wire 1 9 D $end
$var wire 1 % ENABLE $end
$var wire 1 ( RST $end
$var reg 1 : Q $end
$upscope $end
$scope module F4F3 $end
$var wire 1 # CLK $end
$var wire 1 ; D $end
$var wire 1 % ENABLE $end
$var wire 1 ( RST $end
$var reg 1 < Q $end
$upscope $end
$scope module F4F4 $end
$var wire 1 # CLK $end
$var wire 1 = D $end
$var wire 1 % ENABLE $end
$var wire 1 ( RST $end
$var reg 1 > Q $end
$upscope $end
$upscope $end
$scope module Ju88 $end
$var wire 1 # CLK $end
$var wire 4 ? D [3:0] $end
$var wire 1 % ENABLE $end
$var wire 1 ( RST $end
$var wire 4 @ Q [3:0] $end
$scope module F4F1 $end
$var wire 1 # CLK $end
$var wire 1 A D $end
$var wire 1 % ENABLE $end
$var wire 1 ( RST $end
$var reg 1 B Q $end
$upscope $end
$scope module F4F2 $end
$var wire 1 # CLK $end
$var wire 1 C D $end
$var wire 1 % ENABLE $end
$var wire 1 ( RST $end
$var reg 1 D Q $end
$upscope $end
$scope module F4F3 $end
$var wire 1 # CLK $end
$var wire 1 E D $end
$var wire 1 % ENABLE $end
$var wire 1 ( RST $end
$var reg 1 F Q $end
$upscope $end
$scope module F4F4 $end
$var wire 1 # CLK $end
$var wire 1 G D $end
$var wire 1 % ENABLE $end
$var wire 1 ( RST $end
$var reg 1 H Q $end
$upscope $end
$upscope $end
$upscope $end
$upscope $end
$upscope $end
$enddefinitions $end
#0
$dumpvars
xH
xG
xF
xE
xD
xC
xB
xA
bx @
bx ?
x>
x=
x<
x;
x:
x9
x8
x7
bx 6
bx 5
bx 4
bx 3
bx 2
bx 1
b0 0
bx /
bx .
bx -
bx ,
bx +
bx *
b0 )
0(
0'
b0 &
0%
0$
0#
bx "
bx !
$end
#1
17
09
1;
1=
1A
0C
1E
1G
b1011 5
b1011 ?
b10101011 ,
b10101011 .
b10101011 2
b0 -
b0 /
b0 1
08
0:
0<
b0 "
b0 +
b0 4
b0 6
0>
0B
0D
0F
b0 !
b0 *
b0 3
b0 @
0H
1#
1(
#2
0#
0(
#3
0=
0G
b1010 5
b1010 ?
b1010 ,
b1010 .
b1010 2
b1 -
b1 /
b1 1
1#
1$
#4
0#
1%
#5
1=
1G
b1011 5
b1011 ?
1F
b1010 !
b1010 *
b1010 3
b1010 @
1B
1<
b1010 "
b1010 +
b1010 4
b1010 6
18
b1011 ,
b1011 .
b1011 2
b10 -
b10 /
b10 1
b1 &
b1 )
b1 0
1#
#6
0#
#7
19
0;
0=
1C
0E
0G
b1100 5
b1100 ?
b1100 ,
b1100 .
b1100 2
b11 -
b11 /
b11 1
b1011 "
b1011 +
b1011 4
b1011 6
1>
b1011 !
b1011 *
b1011 3
b1011 @
1H
1#
#8
0#
#9
1=
1G
b1101 5
b1101 ?
0H
0F
b1100 !
b1100 *
b1100 3
b1100 @
1D
0>
0<
b1100 "
b1100 +
b1100 4
b1100 6
1:
b1101 ,
b1101 .
b1101 2
b100 -
b100 /
b100 1
1#
#10
0#
#11
07
09
0A
0C
b1 5
b1 ?
b1 ,
b1 .
b1 2
b101 -
b101 /
b101 1
b1101 "
b1101 +
b1101 4
b1101 6
1>
b1101 !
b1101 *
b1101 3
b1101 @
1H
1#
#12
0#
#13
0D
b1 !
b1 *
b1 3
b1 @
0B
0:
b1 "
b1 +
b1 4
b1 6
08
b100001 ,
b100001 .
b100001 2
b110 -
b110 /
b110 1
1#
#14
0#
#15
19
1;
0=
1C
1E
0G
b110 5
b110 ?
b1000110 ,
b1000110 .
b1000110 2
b111 -
b111 /
b111 1
1#
#16
0#
#17
17
09
1A
0C
b1010 5
b1010 ?
0H
1F
b110 !
b110 *
b110 3
b110 @
1D
0>
1<
b110 "
b110 +
b110 4
b110 6
1:
b10011010 ,
b10011010 .
b10011010 2
b1000 -
b1000 /
b1000 1
1#
#18
0#
#19
1=
1G
b1011 5
b1011 ?
b10011011 ,
b10011011 .
b10011011 2
b1001 -
b1001 /
b1001 1
18
b1010 "
b1010 +
b1010 4
b1010 6
0:
1B
b1010 !
b1010 *
b1010 3
b1010 @
0D
1#
#20
0#
#21
19
0;
0=
1C
0E
0G
b1100 5
b1100 ?
b1011 !
b1011 *
b1011 3
b1011 @
1H
b1011 "
b1011 +
b1011 4
b1011 6
1>
b1011100 ,
b1011100 .
b1011100 2
b1010 -
b1010 /
b1010 1
1#
#22
0#
#23
09
0C
b1000 5
b1000 ?
b1000 ,
b1000 .
b1000 2
b1011 -
b1011 /
b1011 1
1:
0<
b1100 "
b1100 +
b1100 4
b1100 6
0>
1D
0F
b1100 !
b1100 *
b1100 3
b1100 @
0H
1#
#24
0#
#25
07
19
1=
0A
1C
1G
b101 5
b101 ?
b1000 !
b1000 *
b1000 3
b1000 @
0D
b1000 "
b1000 +
b1000 4
b1000 6
0:
b101 ,
b101 .
b101 2
b1100 -
b1100 /
b1100 1
1#
#26
0#
#27
1;
0=
1E
0G
b110 5
b110 ?
b110110 ,
b110110 .
b110110 2
b1101 -
b1101 /
b1101 1
08
1:
b101 "
b101 +
b101 4
b101 6
1>
0B
1D
b101 !
b101 *
b101 3
b101 @
1H
1#
#28
0#
#29
09
0;
1=
0C
0E
1G
b1 5
b1 ?
0H
b110 !
b110 *
b110 3
b110 @
1F
0>
b110 "
b110 +
b110 4
b110 6
1<
b1100001 ,
b1100001 .
b1100001 2
b1110 -
b1110 /
b1110 1
1#
#30
0#
#31
b1 ,
b1 .
b1 2
b1111 -
b1111 /
b1111 1
0:
0<
b1 "
b1 +
b1 4
b1 6
1>
0D
0F
b1 !
b1 *
b1 3
b1 @
1H
1#
#32
0#
#33
1;
0=
1E
0G
b10 5
b10 ?
b10 ,
b10 .
b10 2
b10000 -
b10000 /
b10000 1
1#
#34
0#
#35
1=
1G
b11 5
b11 ?
b11 ,
b11 .
b11 2
b10001 -
b10001 /
b10001 1
1<
b10 "
b10 +
b10 4
b10 6
0>
1F
b10 !
b10 *
b10 3
b10 @
0H
1#
#36
0#
#37
19
0=
1C
0G
b110 5
b110 ?
b11 !
b11 *
b11 3
b11 @
1H
b11 "
b11 +
b11 4
b11 6
1>
b110 ,
b110 .
b110 2
b10010 -
b10010 /
b10010 1
1#
#38
0#
#39
09
1=
0C
1G
b11 5
b11 ?
b1000011 ,
b1000011 .
b1000011 2
b10011 -
b10011 /
b10011 1
1:
b110 "
b110 +
b110 4
b110 6
0>
1D
b110 !
b110 *
b110 3
b110 @
0H
1#
#40
0#
#41
17
19
0;
1A
1C
0E
b1101 5
b1101 ?
1H
b11 !
b11 *
b11 3
b11 @
0D
1>
b11 "
b11 +
b11 4
b11 6
0:
b1001101 ,
b1001101 .
b1001101 2
b10100 -
b10100 /
b10100 1
1#
#42
0#
#43
0=
0G
b1100 5
b1100 ?
b10101100 ,
b10101100 .
b10101100 2
b10101 -
b10101 /
b10101 1
18
1:
b1101 "
b1101 +
b1101 4
b1101 6
0<
1B
1D
b1101 !
b1101 *
b1101 3
b1101 @
0F
1#
#44
0#
#45
1=
1G
b1101 5
b1101 ?
b1100 !
b1100 *
b1100 3
b1100 @
0H
b1100 "
b1100 +
b1100 4
b1100 6
0>
b10111101 ,
b10111101 .
b10111101 2
b10110 -
b10110 /
b10110 1
1#
#46
0#
#47
09
1;
0=
0C
1E
0G
b1010 5
b1010 ?
b11101010 ,
b11101010 .
b11101010 2
b10111 -
b10111 /
b10111 1
b1101 "
b1101 +
b1101 4
b1101 6
1>
b1101 !
b1101 *
b1101 3
b1101 @
1H
1#
#48
0#
#49
19
1C
b1110 5
b1110 ?
0H
1F
b1010 !
b1010 *
b1010 3
b1010 @
0D
0>
1<
b1010 "
b1010 +
b1010 4
b1010 6
0:
b11111110 ,
b11111110 .
b11111110 2
b11000 -
b11000 /
b11000 1
1#
#50
0#
#51
0;
0E
b1100 5
b1100 ?
b11111100 ,
b11111100 .
b11111100 2
b11001 -
b11001 /
b11001 1
b1110 "
b1110 +
b1110 4
b1110 6
1:
b1110 !
b1110 *
b1110 3
b1110 @
1D
1#
#52
0#
#53
09
1;
0C
1E
b1010 5
b1010 ?
b1100 !
b1100 *
b1100 3
b1100 @
0F
b1100 "
b1100 +
b1100 4
b1100 6
0<
b11011010 ,
b11011010 .
b11011010 2
b11010 -
b11010 /
b11010 1
1#
#54
0#
#55
b10111010 ,
b10111010 .
b10111010 2
b11011 -
b11011 /
b11011 1
0:
b1010 "
b1010 +
b1010 4
b1010 6
1<
0D
b1010 !
b1010 *
b1010 3
b1010 @
1F
1#
#56
0#
#57
19
0;
1=
1C
0E
1G
b1101 5
b1101 ?
b11001101 ,
b11001101 .
b11001101 2
b11100 -
b11100 /
b11100 1
1#
#58
0#
#59
1;
0=
1E
0G
b1110 5
b1110 ?
b10101110 ,
b10101110 .
b10101110 2
b11101 -
b11101 /
b11101 1
1:
0<
b1101 "
b1101 +
b1101 4
b1101 6
1>
1D
0F
b1101 !
b1101 *
b1101 3
b1101 @
1H
1#
