Laboratorios/Lab08Digital1Gar19085/Ejercicio01/Contador.v
//UNIVERSIDAD DEL VALLE DE GUATEMALA
//CONTADOR 
//LAB08
//RODRIGO GARCÍA 19085

module Counter(RST, CLK, ENABLE, COUNT, LOAD, E);
input RST, CLK, ENABLE;
input wire [11:0] E;
output [11:0] COUNT;
reg [11:0] COUNT;

always @ (posedge CLK or posedge RST)
    if  (ENABLE) begin
        COUNT <= COUNT + 1;
    end 
    else if (LOAD) begin
        COUNT <= E;
    end
    else if (RST) begin
         COUNT <= 0;   
    end
endmodule

Laboratorios/Lab08Digital1Gar19085/Ejercicio01/Contador_tb.v
//testbench

module testbench();

reg CLK, RST, LOAD, ENABLE; 
reg [11:0] E;
wire [11:0] COUNT;

        always 
            begin 
                CLK <= 0; RST <= 0; #1 CLK <= 1; #1;
            end

Counter Ju88(CLK, RST, ENABLE, LOAD, E, COUNT);

    initial begin
        $display("\n");
        $display("Ejercicio 1");
        $display("CLK | RST | ENABLE |LOAD | E | COUNT");
        $monitor("%b | %b | %b | %b | %b | %b", CLK, RST, ENABLE, LOAD, E, COUNT);
        CLK = 0; RST = 0; ENABLE = 0; LOAD = 0; E = 000000000000;
        #1  RST = 1;
        #1  RST = 0; 
        #1  RST = 0;
        #4  LOAD = 1; E = 12'b000011001100;
        #2  ENABLE = 1; LOAD = 0;
        #50  RST = 1; ENABLE = 0;
        #2  RST = 0;  
        #2  LOAD = 1;
        #2  ENABLE = 1;
        #2  LOAD = 0;
        #2  LOAD = 1; E = 12'b001011111100;
        #20  LOAD = 0;

    end

    always 
        #1 CLK = ~CLK;

    initial 
        #200 $finish;

        initial begin
            $dumpfile("Contador_tb.vcd");
            $dumpvars(0, testbench);
        end

endmodule

Laboratorios/Lab08Digital1Gar19085/Ejercicio01/Contador_tb.vcd
$date
	Sat Oct 24 17:01:05 2020
$end
$version
	Icarus Verilog
$end
$timescale
	1ps
$end
$scope module testbench $end
$var wire 12 ! COUNT [11:0] $end
$var reg 1 " CLK $end
$var reg 12 # E [11:0] $end
$var reg 1 $ ENABLE $end
$var reg 1 % LOAD $end
$var reg 1 & RST $end
$scope module Ju88 $end
$var wire 1 & CLK $end
$var wire 12 ' E [11:0] $end
$var wire 1 $ ENABLE $end
$var wire 1 % LOAD $end
$var wire 1 " RST $end
$var reg 12 ( COUNT [11:0] $end
$upscope $end
$upscope $end
$enddefinitions $end
#0
$dumpvars
bx (
b0 '
0&
0%
0$
b0 #
0"
bx !
$end
#1
b0 !
b0 (
1"
1&
#2
0"
0&
#3
1"
#4
0"
#5
1"
#6
0"
#7
b11001100 !
b11001100 (
1"
b11001100 #
b11001100 '
1%
#8
0"
#9
b11001101 !
b11001101 (
1"
0%
1$
#10
0"
#11
b11001110 !
b11001110 (
1"
#12
0"
#13
b11001111 !
b11001111 (
1"
#14
0"
#15
b11010000 !
b11010000 (
1"
#16
0"
#17
b11010001 !
b11010001 (
1"
#18
0"
#19
b11010010 !
b11010010 (
1"
#20
0"
#21
b11010011 !
b11010011 (
1"
#22
0"
#23
b11010100 !
b11010100 (
1"
#24
0"
#25
b11010101 !
b11010101 (
1"
#26
0"
#27
b11010110 !
b11010110 (
1"
#28
0"
#29
b11010111 !
b11010111 (
1"
#30
0"
#31
b11011000 !
b11011000 (
1"
#32
0"
#33
b11011001 !
b11011001 (
1"
#34
0"
#35
b11011010 !
b11011010 (
1"
#36
0"
#37
b11011011 !
b11011011 (
1"
#38
0"
#39
b11011100 !
b11011100 (
1"
#40
0"
#41
b11011101 !
b11011101 (
1"
#42
0"
#43
b11011110 !
b11011110 (
1"
#44
0"
#45
b11011111 !
b11011111 (
1"
#46
0"
#47
b11100000 !
b11100000 (
1"
#48
0"
#49
b11100001 !
b11100001 (
1"
#50
0"
#51
b11100010 !
b11100010 (
1"
#52
0"
#53
b11100011 !
b11100011 (
1"
#54
0"
#55
b11100100 !
b11100100 (
1"
#56
0"
#57
b11100101 !
b11100101 (
1"
#58
0"
#59
b0 !
b0 (
1"
0$
1&
#60
0&
0"
#61
1"
#62
0"
#63
b11001100 !
b11001100 (
1"
1%
#64
0"
#65
1"
1$
#66
0"
#67
b11001101 !
b11001101 (
1"
0%
#68
0"
#69
b1011111100 !
b1011111100 (
1"
b1011111100 #
b1011111100 '
1%
#70
0"
#71
1"
#72
0"
#73
1"
#74
0"
#75
1"
#76
0"
#77
1"
#78
0"
#79
1"
#80
0"
#81
1"
#82
0"
#83
1"
#84
0"
#85
1"
#86
0"
#87
1"
#88
0"
#89
b1011111101 !
b1011111101 (
1"
0%
#90
0"
#91
b1011111110 !
b1011111110 (
1"
#92
0"
#93
b1011111111 !
b1011111111 (
1"
#94
0"
#95
b1100000000 !
b1100000000 (
1"
#96
0"
#97
b1100000001 !
b1100000001 (
1"
#98
0"
#99
b1100000010 !
b1100000010 (
1"
#100
0"
#101
b1100000011 !
b1100000011 (
1"
#102
0"
#103
b1100000100 !
b1100000100 (
1"
#104
0"
#105
b1100000101 !
b1100000101 (
1"
#106
0"
#107
b1100000110 !
b1100000110 (
1"
#108
0"
#109
b1100000111 !
b1100000111 (
1"
#110
0"
#111
b1100001000 !
b1100001000 (
1"
#112
0"
#113
b1100001001 !
b1100001001 (
1"
#114
0"
#115
b1100001010 !
b1100001010 (
1"
#116
0"
#117
b1100001011 !
b1100001011 (
1"
#118
0"
#119
b1100001100 !
b1100001100 (
1"
#120
0"
#121
b1100001101 !
b1100001101 (
1"
#122
0"
#123
b1100001110 !
b1100001110 (
1"
#124
0"
#125
b1100001111 !
b1100001111 (
1"
#126
0"
#127
b1100010000 !
b1100010000 (
1"
#128
0"
#129
b1100010001 !
b1100010001 (
1"
#130
0"
#131
b1100010010 !
b1100010010 (
1"
#132
0"
#133
b1100010011 !
b1100010011 (
1"
#134
0"
#135
b1100010100 !
b1100010100 (
1"
#136
0"
#137
b1100010101 !
b1100010101 (
1"
#138
0"
#139
b1100010110 !
b1100010110 (
1"
#140
0"
#141
b1100010111 !
b1100010111 (
1"
#142
0"
#143
b1100011000 !
b1100011000 (
1"
#144
0"
#145
b1100011001 !
b1100011001 (
1"
#146
0"
#147
b1100011010 !
b1100011010 (
1"
#148
0"
#149
b1100011011 !
b1100011011 (
1"
#150
0"
#151
b1100011100 !
b1100011100 (
1"
#152
0"
#153
b1100011101 !
b1100011101 (
1"
#154
0"
#155
b1100011110 !
b1100011110 (
1"
#156
0"
#157
b1100011111 !
b1100011111 (
1"
#158
0"
#159
b1100100000 !
b1100100000 (
1"
#160
0"
#161
b1100100001 !
b1100100001 (
1"
#162
0"
#163
b1100100010 !
b1100100010 (
1"
#164
0"
#165
b1100100011 !
b1100100011 (
1"
#166
0"
#167
b1100100100 !
b1100100100 (
1"
#168
0"
#169
b1100100101 !
b1100100101 (
1"
#170
0"
#171
b1100100110 !
b1100100110 (
1"
#172
0"
#173
b1100100111 !
b1100100111 (
1"
#174
0"
#175
b1100101000 !
b1100101000 (
1"
#176
0"
#177
b1100101001 !
b1100101001 (
1"
#178
0"
#179
b1100101010 !
b1100101010 (
1"
#180
0"
#181
b1100101011 !
b1100101011 (
1"
#182
0"
#183
b1100101100 !
b1100101100 (
1"
#184
0"
#185
b1100101101 !
b1100101101 (
1"
#186
0"
#187
b1100101110 !
b1100101110 (
1"
#188
0"
#189
b1100101111 !
b1100101111 (
1"
#190
0"
#191
b1100110000 !
b1100110000 (
1"
#192
0"
#193
b1100110001 !
b1100110001 (
1"
#194
0"
#195
b1100110010 !
b1100110010 (
1"
#196
0"
#197
b1100110011 !
b1100110011 (
1"
#198
0"
#199
b1100110100 !
b1100110100 (
1"
