Laboratorios/Lab09Digital1Gar19085/Ejercicio05/ROM.v
//UNIVERSIDAD DEL VALLE 
//LAB09
//Rodrigo GArcía19085


module  ROM(IN, OUT);
    input   [6:0] IN;
    output reg [12:0] OUT;
    
    always @ (*)
    begin
        case (IN)
        7'bxxxxxx0:     OUT = 13'b1000000001000;
        7'b00001x1:     OUT = 13'b0100000001000;
        7'b00000x1:     OUT = 13'b1000000001000;
        7'b00011x1:     OUT = 13'b1000000001000;
        7'b00010x1:     OUT = 13'b0100000001000;
        7'b0010xx1:     OUT = 13'b0001001000010;
        7'b0011xx1:     OUT = 13'b1001001100000;
        7'b0100xx1:     OUT = 13'b0011010000010;
        7'b0101xx1:     OUT = 13'b0011010000100;
        7'b0110xx1:     OUT = 13'b1011010100000;
        7'b0111xx1:     OUT = 13'b1000000111000;
        7'b1000x11:     OUT = 13'b0100000001000;
        7'b1000x01:     OUT = 13'b1000000001000;
        7'b1001x11:     OUT = 13'b1000000001000;
        7'b1001x01:     OUT = 13'b0100000001000;
        7'b1010xx1:     OUT = 13'b0011011000010;
        7'b1011xx1:     OUT = 13'b1011011100000;
        7'b1100xx1:     OUT = 13'b0100000001000;
        7'b1101xx1:     OUT = 13'b0000000001001;
        7'b1110xx1:     OUT = 13'b0011100000010;
        7'b1111xx1:     OUT = 13'b1011100100000;
            default:    OUT = 13'b1000000001000;
        endcase
    end
endmodule

Laboratorios/Lab09Digital1Gar19085/Ejercicio05/ROM_tb.v


module testbench();

reg [6:0]IN;
wire [12:0] OUT;

ROM R6(IN, OUT);

initial begin
        $display("\n");
        $display("Buffer");
        $display("IN |  OUT");
        $monitor("%b  |   %b", IN, OUT);
        IN = 0;
        #1 IN = 7'bxxxxxx0;
        #1 IN = 7'b00001x1;     
        #1 IN = 7'b00000x1;       
        #1 IN = 7'b00011x1;       
        #1 IN = 7'b00010x1;       
        #1 IN = 7'b0010xx1;       
        #1 IN = 7'b0011xx1;       
        #1 IN = 7'b0100xx1;       
        #1 IN = 7'b0101xx1;       
        #1 IN = 7'b0110xx1;       
        #1 IN = 7'b0111xx1;       
        #1 IN = 7'b1000x11;       
        #1 IN = 7'b1000x01;       
        #1 IN = 7'b1001x11;       
        #1 IN = 7'b1001x01;       
        #1 IN = 7'b1010xx1;       
        #1 IN = 7'b1011xx1;       
        #1 IN = 7'b1100xx1;       
        #1 IN = 7'b1101xx1;     
        #1 IN = 7'b1110xx1;     
        #1 IN = 7'b1111xx1;   
end        


        initial begin
            $dumpfile("ROM_tb.vcd");
            $dumpvars(0, testbench);
        end

endmodule

Laboratorios/Lab09Digital1Gar19085/Ejercicio05/ROM_tb.vcd
$date
	Fri Oct 30 20:17:37 2020
$end
$version
	Icarus Verilog
$end
$timescale
	1ps
$end
$scope module testbench $end
$var wire 13 ! OUT [12:0] $end
$var reg 7 " IN [6:0] $end
$scope module R6 $end
$var wire 7 # IN [6:0] $end
$var reg 13 $ OUT [12:0] $end
$upscope $end
$upscope $end
$enddefinitions $end
#0
$dumpvars
b1000000001000 $
b0 #
b0 "
b1000000001000 !
$end
#1
bx0 "
bx0 #
#2
b100000001000 !
b100000001000 $
b1x1 "
b1x1 #
#3
b1000000001000 !
b1000000001000 $
b0x1 "
b0x1 #
#4
b11x1 "
b11x1 #
#5
b100000001000 !
b100000001000 $
b10x1 "
b10x1 #
#6
b1001000010 !
b1001000010 $
b10xx1 "
b10xx1 #
#7
b1001001100000 !
b1001001100000 $
b11xx1 "
b11xx1 #
#8
b11010000010 !
b11010000010 $
b100xx1 "
b100xx1 #
#9
b11010000100 !
b11010000100 $
b101xx1 "
b101xx1 #
#10
b1011010100000 !
b1011010100000 $
b110xx1 "
b110xx1 #
#11
b1000000111000 !
b1000000111000 $
b111xx1 "
b111xx1 #
#12
b100000001000 !
b100000001000 $
b1000x11 "
b1000x11 #
#13
b1000000001000 !
b1000000001000 $
b1000x01 "
b1000x01 #
#14
b1001x11 "
b1001x11 #
#15
b100000001000 !
b100000001000 $
b1001x01 "
b1001x01 #
#16
b11011000010 !
b11011000010 $
b1010xx1 "
b1010xx1 #
#17
b1011011100000 !
b1011011100000 $
b1011xx1 "
b1011xx1 #
#18
b100000001000 !
b100000001000 $
b1100xx1 "
b1100xx1 #
#19
b1001 !
b1001 $
b1101xx1 "
b1101xx1 #
#20
b11100000010 !
b11100000010 $
b1110xx1 "
b1110xx1 #
#21
b1011100100000 !
b1011100100000 $
b1111xx1 "
b1111xx1 #
