Laboratorios/Lab09Digital1Gar19085/Ejercicio02/FFT.v



module FFD1 (input CLK, RST, ENABLE, D,
            output reg Q);
        always @ (posedge CLK or posedge RST)begin
            if (RST) begin
                Q <= 1'b0;
            end
            else if (ENABLE) begin
                Q <= D;
            end
        end   
endmodule


module FFT(input wire CLK, RST, ENABLE,
            output wire Y);
        wire D;    
        not (D, Y);
        FFD1 Ju88(CLK, RST, ENABLE, D, Y);
endmodule

Laboratorios/Lab09Digital1Gar19085/Ejercicio02/FFT_tb.v



module Testbench();



reg CLK, RST, ENABLE, T;
wire Y;


FFT Ju87(CLK, RST, ENABLE,Y);


        always 
            begin 
                CLK <= 0; RST <= 0; #1 CLK <= 1; #1;
            end

            
    initial begin
        $display("\n");
        $display("FLIP-FLOP T");
        $display("CLK | RST | ENABLE | T | Y");
        $monitor("%b  | %b  |    %b  | %b | %b ",
                CLK,RST, ENABLE, T, Y);
        CLK = 0; RST = 0; ENABLE = 0; T = 0;        
     #1  RST = 1;
     #1  RST = 0;
     #2  ENABLE = 1;  
     #2  T = 1;
    end

   always
    #1  CLK = ~CLK;
  
   initial 
        #25 $finish;

        initial begin
            $dumpfile("FFT_Tb.vcd");
            $dumpvars(0, Testbench);
        end

        endmodule

Laboratorios/Lab09Digital1Gar19085/Ejercicio02/FFT_Tb.vcd
$date
	Fri Oct 30 18:41:23 2020
$end
$version
	Icarus Verilog
$end
$timescale
	1ps
$end
$scope module Testbench $end
$var wire 1 ! Y $end
$var reg 1 " CLK $end
$var reg 1 # ENABLE $end
$var reg 1 $ RST $end
$var reg 1 % T $end
$scope module Ju87 $end
$var wire 1 " CLK $end
$var wire 1 & D $end
$var wire 1 # ENABLE $end
$var wire 1 $ RST $end
$var wire 1 ! Y $end
$scope module Ju88 $end
$var wire 1 " CLK $end
$var wire 1 & D $end
$var wire 1 # ENABLE $end
$var wire 1 $ RST $end
$var reg 1 ! Q $end
$upscope $end
$upscope $end
$upscope $end
$enddefinitions $end
#0
$dumpvars
x&
0%
0$
0#
0"
x!
$end
#1
1&
0!
1"
1$
#2
0"
0$
#3
1"
#4
0"
1#
#5
0&
1!
1"
#6
0"
1%
#7
1&
0!
1"
#8
0"
#9
0&
1!
1"
#10
0"
#11
1&
0!
1"
#12
0"
#13
0&
1!
1"
#14
0"
#15
1&
0!
1"
#16
0"
#17
0&
1!
1"
#18
0"
#19
1&
0!
1"
#20
0"
#21
0&
1!
1"
#22
0"
#23
1&
0!
1"
#24
0"
#25
0&
1!
1"
