Proyecto 2/uP.v
/*
Universidad del Valle de Guatemala 
Digital 1
Rodrigo García 19085
Proyecto 2  uP
*/

//FlipFLops Base para los demas  modulños
module FFD1 (input clock, RST, ENABLE, D,
            output reg Q);
        always @ (posedge clock or posedge RST)begin
            if (RST) begin
                Q <= 1'b0;
            end
            else if (ENABLE) begin
                Q <= D;
            end
        end   
endmodule

//Flip-Flop de 4 realizado con flip flops de 1 bit
module FFD4 (input clock, RST, ENABLE, input [3:0] D, 
            output wire [3:0]Q);
        FFD1 F4F1(clock, RST, ENABLE,  D[3], Q[3]);
        FFD1 F4F2(clock, RST, ENABLE, D[2], Q[2]);
        FFD1 F4F3(clock, RST, ENABLE,  D[1], Q[1]);
        FFD1 F4F4(clock, RST, ENABLE, D[0], Q[0]);
endmodule             

//Modulo respectivo al funcionamiento del phase
//Es un Flip Flop tipo T
module PHASE(input wire clock, RST, ENABLE, 
            output wire Y);                 
        wire D;                             
        not (D, Y);                         
        FFD1 Ju88(clock, RST, ENABLE, D, Y);
endmodule

//Modulo respectivo al funcionamiento de los Flags
//Es un Flip-Flop de 2 bits
module FLAGS(input clock, RST, ENABLE, input [1:0] D, 
            output wire [1:0]Q);
    //Se realizo por medio de Flip-Flops de 1 bit
    FFD1 FD1(clock, RST, ENABLE,  D[0], Q[0]);
    FFD1 FD2(clock, RST, ENABLE,  D[1], Q[1]);
endmodule

//Modulo respectivo al funcionamiento del Program Counter
module Counter(RST, clock, ENABLE, LOAD, E, PC);
    input RST, clock, ENABLE, LOAD;
    input wire [11:0] E;
    output [11:0] PC;
    reg [11:0] PC;
    //Se realizan las condicionales para el funcionamiento del mismo
    always @ (posedge clock or posedge RST)
        if (LOAD) begin
            PC <= E;
        end
    else if  (ENABLE) begin
        if (~LOAD);
        PC <= PC + 1;
        end 
    else if (RST) begin
        PC <= 0;   
        end
endmodule

//Modulo respectivo al funcionamiento de la ROM
module  ROM4Kx8(address, Dout);
    input   [11:0] address;
    output  [7:0] Dout;
    
    assign Dout = memory[address];
    reg [7:0]   memory[0:4095];
    //Se asigna la instruccion "readmemh" para que pueda leer la información en el .list guardada en hexadecimal
    initial begin
        $readmemh("memory.list", memory);
    end
endmodule    

//Modulo respectivo al funcionamiento del FETCH
module FETCH(input clock, RST, ENABLE, input [7:0] D, 
            output wire [3:0]Q1,
            output wire [3:0]Q2);
        //Se implemento con 2 Flip-Flops de 4 bits
        FFD4 Ju87(clock, RST, ENABLE,  D[7:4], Q1[3:0]);
        FFD4 Ju88(clock, RST, ENABLE,  D[3:0], Q2[3:0]);
endmodule   

//Modulo respectivo al funcionamiento de los Buffers Triestado
module BUS(DPS, AC, OUT);
    input [3:0] DPS;
    input AC;
    output reg [3:0] OUT;
    //Se genera un case para poder indicar las instrucciones del bus
    always @ (*)
    begin
        case (AC)
            1'b0:   OUT = 4'bzzzz;
            1'b1:   OUT = DPS;
            default: OUT = 4'bzzzz;
        endcase
    end    

endmodule    
//Modulo respectivo al funcionamiento del acumulador
//Es un Flip-Flop de 4 bits
module ACCUMULATOR (input clock, RST, ENABLE, input [3:0] D, 
                    output wire [3:0]Q);
        //Se realizo por medio de Flip-Flops de 1 bit
        FFD1 F4F1(clock, RST, ENABLE,  D[3], Q[3]);
        FFD1 F4F2(clock, RST, ENABLE, D[2], Q[2]);
        FFD1 F4F3(clock, RST, ENABLE,  D[1], Q[1]);
        FFD1 F4F4(clock, RST, ENABLE, D[0], Q[0]);
endmodule    

//Modulo respectivo al funcionamiento de la ALU
module  ALU(A, B, SEL, C, ZERO, OUT);
    input   [3:0] A, B;
    input   [2:0] SEL;
    output  [3:0] OUT;  
    output  C, ZERO;
    // C = Carry
    reg [4:0] IR; //Registro interno
    //Función case para poder realizar las instrucciones de la ALU
    always @ (A, B, SEL)
        case (SEL)
            3'b000: IR = A;
            3'b001: IR = A - B;
            3'b010: IR = B;
            3'b011: IR = A + B;
            3'b100: IR = {1'b0, ~(A & B)};
            default: IR = 5'b10101;
        endcase
    
    assign OUT = IR[3:0];
    assign C = IR[4];
    assign ZERO = ~(IR[3] | IR[2] | IR[1] | IR[0]);
    
endmodule    

//Modulo respectivo al funcionamiento de la RAM
module  RAM4Kx4(address, cs, we, data);

    input [11:0] address;
    input cs, we;
    inout [3:0] data;

    //cs = Chip Select
    //we = Write Enable

    reg [3:0] data_out;
    reg [3:0] mem [0:4095];
    //Se asignan las instrucciones para el funcionamiento de la RAM
    assign data = (cs && ! we) ? data_out : 8'bz;
    //Se indican las condicionales para que pueda funcionar
    always @ (address or data or cs or we)
    begin : MEM_WRITE
        if (cs && we) begin
            mem[address] = data;
        end
    end

    always @ (address or cs or we)
    begin : MEM_READ
        if (cs && ! we) begin
            data_out = mem[address];
        end    
    end    

endmodule

//Modulo respectivo al funcionamiento del Decoder
module  DECODE(IN, OUT);
    input   [6:0] IN;
    output  [12:0] OUT;
    
    reg [12:0] signalsReg;
    /*Se implementa un casez para poder recrear la tabla de funciones del procesador
    así lee que bits especificos están en uso  y cuales no para realizar una instrucción*/
    always @ (IN)
        casez(IN)
            // any
            7'b????_??0: signalsReg <= 13'b1000_000_001000;
            // JC
            7'b0000_1?1: signalsReg <= 13'b0100_000_001000;
            7'b0000_0?1: signalsReg <= 13'b1000_000_001000;
            // JNC
            7'b0001_1?1: signalsReg <= 13'b1000_000_001000;
            7'b0001_0?1: signalsReg <= 13'b0100_000_001000;
            // CMPI
            7'b0010_??1: signalsReg <= 13'b0001_001_000010;
            // CMPM
            7'b0011_??1: signalsReg <= 13'b1001_001_100000;
            // LIT
            7'b0100_??1: signalsReg <= 13'b0011_010_000010;
            // IN
            7'b0101_??1: signalsReg <= 13'b0011_010_000100;
            // LD
            7'b0110_??1: signalsReg <= 13'b1011_010_100000;
            // ST
            7'b0111_??1: signalsReg <= 13'b1000_000_111000;
            // JZ
            7'b1000_?11: signalsReg <= 13'b0100_000_001000;
            7'b1000_?01: signalsReg <= 13'b1000_000_001000;
            // JNZ
            7'b1001_?11: signalsReg <= 13'b1000_000_001000;
            7'b1001_?01: signalsReg <= 13'b0100_000_001000;
            // ADDI
            7'b1010_??1: signalsReg <= 13'b0011_011_000010;
            // ADDM
            7'b1011_??1: signalsReg <= 13'b1011_011_100000;
            // JMP
            7'b1100_??1: signalsReg <= 13'b0100_000_001000;
            // OUT
            7'b1101_??1: signalsReg <= 13'b0000_000_001001;
            // NANDI
            7'b1110_??1: signalsReg <= 13'b0011_100_000010;
            // NANDM
            7'b1111_??1: signalsReg <= 13'b1011_100_100000;
            default: signalsReg <= 13'b1111111111111;
        endcase
        
    assign OUT = signalsReg;
endmodule    

//Modulo principal para unir todos los modulos que conforman partes del uProcesador 
module  uP(clock, reset, pushbuttons, phase,
            c_flag, z_flag, instr, oprnd, data_bus, FF_out, 
            accu, program_byte, address_RAM, PC);
    //Se indican que variables son entradas y cuales son salidas con su respectivo tamaño de bits.         
    input wire clock, reset;
    input wire [3:0] pushbuttons;
    output wire c_flag, z_flag, phase;
    output wire [11:0] PC, address_RAM;
    output wire [3:0] instr, oprnd, data_bus, FF_out, accu; 
    output wire [7:0] program_byte;

    wire [12:0] Decodx;
    wire [6:0] Decoder;
    wire [3:0] ALU_O;
    wire ZERO;
    wire C;
    //Es necesario concatenar algunas entradas y salidas para llegar al tamaño de bits necesarios para el modulo 
    //correspondiente
    assign address_RAM = {oprnd, program_byte};
    assign Decoder = {instr, c_flag, z_flag, phase};

    //Se llama a cada modulo por aparte para comenzar a unir los modulos, con sus respectivos inputs y outputs
    Counter PzCounter   (reset, clock, Decodx[12], Decodx[11], address_RAM, PC);
    ROM4Kx8 PzRom       (PC, program_byte);
    FETCH   PzFetch     (clock, reset, ~phase, program_byte, instr, oprnd);
    BUS     PzBus1      (oprnd, Decodx[1], data_bus);
    PHASE   PzPhase     (clock, reset, 1'b1, phase);
    FLAGS   PzFlag      (clock, reset, Decodx[9], {C, ZERO}, {c_flag, z_flag});
    DECODE  PzDecode    (Decoder, Decodx);
    ACCUMULATOR PzAccu  (clock, reset, Decodx[10], ALU_O, accu);
    ALU     PzAlu       (accu, data_bus, Decodx[8:6], C, ZERO, ALU_O);
    BUS     PzBus2      (ALU_O, Decodx[3] ,data_bus);
    RAM4Kx4 PzRam       (address_RAM, Decodx[5], Decodx[4], data_bus);
    BUS     PzBusIn     (pushbuttons, Decodx[2] ,data_bus);
    FFD4    FFoutput    (clock, reset, Decodx[0], data_bus, FF_out);
    /*
    Los Decodx[?] corresponden al bit especifico del DECODER, los cuales funcionan como enables
    para los modulos y así realizar las instrucciones especificas del procesador ingresadas en el modulo
    DECODER
    */

endmodule

Proyecto 2/uP_tb.v
module testbench();

    reg clock, reset;
    reg [3:0] pushbuttons;
    wire c_flag, z_flag, phase;
    wire [11:0] PC, address_RAM;
    wire [3:0] instr, oprnd, data_bus, FF_out, accu;
    wire [7:0] program_byte;

    uP uPmodule(.clock(clock),
                .reset(reset),
                .pushbuttons(pushbuttons),
                .phase(phase),
                .c_flag(c_flag),
                .z_flag(z_flag),
                .instr(instr),
                .oprnd(oprnd),
                .accu(accu),
                .data_bus(data_bus),
                .FF_out(FF_out),
                .program_byte(program_byte),
                .PC(PC),
                .address_RAM(address_RAM));

    initial
        #500 $finish;

    always
        #5 clock = ~clock;

    initial begin
        $display("\n");
        $display("MicroProcesador García 19085");
        $display("clock| reset| pushbuttons| phase|  c_flag | z_flag | instr| oprnd| data_bus| FF_out| accu | program_byte| address_RAM |  PC  |");
        $monitor("  %b |  %b  |     %b     |  %b  |    %b   |  %b    |  %b  |  %b  |    %b   |  %b   |  %b  |      %b     |     %b      |  %b  |", 
                clock, reset, pushbuttons, phase, c_flag, z_flag, instr, oprnd, data_bus, FF_out, accu, program_byte, address_RAM, PC);
        clock = 0; pushbuttons = 4'b0101; 
        #2 reset = 1;
        #1 reset = 0;
    end

    initial begin
        $dumpfile("uP_tb.vcd");
        $dumpvars(0, testbench);
    end
endmodule

Proyecto 2/uP_tb.vcd
$date
	Sun Nov 22 18:39:24 2020
$end
$version
	Icarus Verilog
$end
$timescale
	1ps
$end
$scope module testbench $end
$var wire 4 ! data_bus [3:0] $end
$var wire 1 " z_flag $end
$var wire 8 # program_byte [7:0] $end
$var wire 1 $ phase $end
$var wire 4 % oprnd [3:0] $end
$var wire 4 & instr [3:0] $end
$var wire 1 ' c_flag $end
$var wire 12 ( address_RAM [11:0] $end
$var wire 4 ) accu [3:0] $end
$var wire 12 * PC [11:0] $end
$var wire 4 + FF_out [3:0] $end
$var reg 1 , clock $end
$var reg 4 - pushbuttons [3:0] $end
$var reg 1 . reset $end
$scope module uPmodule $end
$var wire 1 , clock $end
$var wire 4 / data_bus [3:0] $end
$var wire 4 0 pushbuttons [3:0] $end
$var wire 1 . reset $end
$var wire 1 " z_flag $end
$var wire 8 1 program_byte [7:0] $end
$var wire 1 $ phase $end
$var wire 4 2 oprnd [3:0] $end
$var wire 4 3 instr [3:0] $end
$var wire 1 ' c_flag $end
$var wire 12 4 address_RAM [11:0] $end
$var wire 4 5 accu [3:0] $end
$var wire 1 6 ZERO $end
$var wire 12 7 PC [11:0] $end
$var wire 4 8 FF_out [3:0] $end
$var wire 13 9 Decodx [12:0] $end
$var wire 7 : Decoder [6:0] $end
$var wire 1 ; C $end
$var wire 4 < ALU_O [3:0] $end
$scope module FFoutput $end
$var wire 4 = D [3:0] $end
$var wire 1 > ENABLE $end
$var wire 1 . RST $end
$var wire 1 , clock $end
$var wire 4 ? Q [3:0] $end
$scope module F4F1 $end
$var wire 1 @ D $end
$var wire 1 > ENABLE $end
$var wire 1 . RST $end
$var wire 1 , clock $end
$var reg 1 A Q $end
$upscope $end
$scope module F4F2 $end
$var wire 1 B D $end
$var wire 1 > ENABLE $end
$var wire 1 . RST $end
$var wire 1 , clock $end
$var reg 1 C Q $end
$upscope $end
$scope module F4F3 $end
$var wire 1 D D $end
$var wire 1 > ENABLE $end
$var wire 1 . RST $end
$var wire 1 , clock $end
$var reg 1 E Q $end
$upscope $end
$scope module F4F4 $end
$var wire 1 F D $end
$var wire 1 > ENABLE $end
$var wire 1 . RST $end
$var wire 1 , clock $end
$var reg 1 G Q $end
$upscope $end
$upscope $end
$scope module PzAccu $end
$var wire 1 H ENABLE $end
$var wire 1 . RST $end
$var wire 1 , clock $end
$var wire 4 I Q [3:0] $end
$var wire 4 J D [3:0] $end
$scope module F4F1 $end
$var wire 1 K D $end
$var wire 1 H ENABLE $end
$var wire 1 . RST $end
$var wire 1 , clock $end
$var reg 1 L Q $end
$upscope $end
$scope module F4F2 $end
$var wire 1 M D $end
$var wire 1 H ENABLE $end
$var wire 1 . RST $end
$var wire 1 , clock $end
$var reg 1 N Q $end
$upscope $end
$scope module F4F3 $end
$var wire 1 O D $end
$var wire 1 H ENABLE $end
$var wire 1 . RST $end
$var wire 1 , clock $end
$var reg 1 P Q $end
$upscope $end
$scope module F4F4 $end
$var wire 1 Q D $end
$var wire 1 H ENABLE $end
$var wire 1 . RST $end
$var wire 1 , clock $end
$var reg 1 R Q $end
$upscope $end
$upscope $end
$scope module PzAlu $end
$var wire 4 S A [3:0] $end
$var wire 4 T B [3:0] $end
$var wire 3 U SEL [2:0] $end
$var wire 1 6 ZERO $end
$var wire 4 V OUT [3:0] $end
$var wire 1 ; C $end
$var reg 5 W IR [4:0] $end
$upscope $end
$scope module PzBus1 $end
$var wire 1 X AC $end
$var wire 4 Y DPS [3:0] $end
$var reg 4 Z OUT [3:0] $end
$upscope $end
$scope module PzBus2 $end
$var wire 1 [ AC $end
$var wire 4 \ DPS [3:0] $end
$var reg 4 ] OUT [3:0] $end
$upscope $end
$scope module PzBusIn $end
$var wire 1 ^ AC $end
$var wire 4 _ DPS [3:0] $end
$var reg 4 ` OUT [3:0] $end
$upscope $end
$scope module PzCounter $end
$var wire 12 a E [11:0] $end
$var wire 1 b ENABLE $end
$var wire 1 c LOAD $end
$var wire 1 . RST $end
$var wire 1 , clock $end
$var reg 12 d PC [11:0] $end
$upscope $end
$scope module PzDecode $end
$var wire 7 e IN [6:0] $end
$var wire 13 f OUT [12:0] $end
$var reg 13 g signalsReg [12:0] $end
$upscope $end
$scope module PzFetch $end
$var wire 1 h ENABLE $end
$var wire 1 . RST $end
$var wire 1 , clock $end
$var wire 4 i Q2 [3:0] $end
$var wire 4 j Q1 [3:0] $end
$var wire 8 k D [7:0] $end
$scope module Ju87 $end
$var wire 4 l D [3:0] $end
$var wire 1 h ENABLE $end
$var wire 1 . RST $end
$var wire 1 , clock $end
$var wire 4 m Q [3:0] $end
$scope module F4F1 $end
$var wire 1 n D $end
$var wire 1 h ENABLE $end
$var wire 1 . RST $end
$var wire 1 , clock $end
$var reg 1 o Q $end
$upscope $end
$scope module F4F2 $end
$var wire 1 p D $end
$var wire 1 h ENABLE $end
$var wire 1 . RST $end
$var wire 1 , clock $end
$var reg 1 q Q $end
$upscope $end
$scope module F4F3 $end
$var wire 1 r D $end
$var wire 1 h ENABLE $end
$var wire 1 . RST $end
$var wire 1 , clock $end
$var reg 1 s Q $end
$upscope $end
$scope module F4F4 $end
$var wire 1 t D $end
$var wire 1 h ENABLE $end
$var wire 1 . RST $end
$var wire 1 , clock $end
$var reg 1 u Q $end
$upscope $end
$upscope $end
$scope module Ju88 $end
$var wire 4 v D [3:0] $end
$var wire 1 h ENABLE $end
$var wire 1 . RST $end
$var wire 1 , clock $end
$var wire 4 w Q [3:0] $end
$scope module F4F1 $end
$var wire 1 x D $end
$var wire 1 h ENABLE $end
$var wire 1 . RST $end
$var wire 1 , clock $end
$var reg 1 y Q $end
$upscope $end
$scope module F4F2 $end
$var wire 1 z D $end
$var wire 1 h ENABLE $end
$var wire 1 . RST $end
$var wire 1 , clock $end
$var reg 1 { Q $end
$upscope $end
$scope module F4F3 $end
$var wire 1 | D $end
$var wire 1 h ENABLE $end
$var wire 1 . RST $end
$var wire 1 , clock $end
$var reg 1 } Q $end
$upscope $end
$scope module F4F4 $end
$var wire 1 ~ D $end
$var wire 1 h ENABLE $end
$var wire 1 . RST $end
$var wire 1 , clock $end
$var reg 1 !" Q $end
$upscope $end
$upscope $end
$upscope $end
$scope module PzFlag $end
$var wire 2 "" D [1:0] $end
$var wire 1 #" ENABLE $end
$var wire 1 . RST $end
$var wire 1 , clock $end
$var wire 2 $" Q [1:0] $end
$scope module FD1 $end
$var wire 1 %" D $end
$var wire 1 #" ENABLE $end
$var wire 1 . RST $end
$var wire 1 , clock $end
$var reg 1 &" Q $end
$upscope $end
$scope module FD2 $end
$var wire 1 '" D $end
$var wire 1 #" ENABLE $end
$var wire 1 . RST $end
$var wire 1 , clock $end
$var reg 1 (" Q $end
$upscope $end
$upscope $end
$scope module PzPhase $end
$var wire 1 )" D $end
$var wire 1 *" ENABLE $end
$var wire 1 . RST $end
$var wire 1 , clock $end
$var wire 1 $ Y $end
$scope module Ju88 $end
$var wire 1 )" D $end
$var wire 1 *" ENABLE $end
$var wire 1 . RST $end
$var wire 1 , clock $end
$var reg 1 $ Q $end
$upscope $end
$upscope $end
$scope module PzRam $end
$var wire 12 +" address [11:0] $end
$var wire 1 ," cs $end
$var wire 4 -" data [3:0] $end
$var wire 1 ." we $end
$var reg 4 /" data_out [3:0] $end
$scope begin MEM_READ $end
$upscope $end
$scope begin MEM_WRITE $end
$upscope $end
$upscope $end
$scope module PzRom $end
$var wire 8 0" Dout [7:0] $end
$var wire 12 1" address [11:0] $end
$upscope $end
$upscope $end
$upscope $end
$enddefinitions $end
#0
$dumpvars
bx 1"
bx 0"
bx /"
x."
bx -"
x,"
bx +"
1*"
x)"
x("
x'"
x&"
x%"
bx $"
x#"
bx ""
x!"
x~
x}
x|
x{
xz
xy
xx
bx w
bx v
xu
xt
xs
xr
xq
xp
xo
xn
bx m
bx l
bx k
bx j
bx i
xh
bx g
bx f
bx e
bx d
xc
xb
bx a
bz `
b101 _
x^
bx ]
bx \
x[
bx Z
bx Y
xX
bx W
bx V
bx U
bx T
bx S
xR
xQ
xP
xO
xN
xM
xL
xK
bx J
bx I
xH
xG
xF
xE
xD
xC
xB
xA
x@
bx ?
x>
bx =
bx <
x;
bx :
bx 9
bx 8
bx 7
x6
bx 5
bx 4
bx 3
bx 2
bx 1
b101 0
bx /
x.
b101 -
0,
bx +
bx *
bx )
bx (
x'
bx &
bx %
x$
bx #
x"
bx !
$end
#2
0@
0B
0D
0F
b0 !
b0 /
b0 =
b0 T
b0 -"
0>
0^
0."
0,"
1[
b0 U
0H
0#"
0X
0c
1b
b1000000001000 9
b1000000001000 f
b1000000001000 g
1%"
16
0Q
0O
0M
0K
b0 ]
0'"
0x
0z
0|
0~
0n
1p
0r
1t
b0 <
b0 J
b0 V
b0 \
b1 ""
0;
b0 v
b101 l
bz Z
1)"
1h
0"
0'
b0 W
b1010000 #
b1010000 1
b1010000 k
b1010000 0"
b0 *
b0 7
b0 d
b0 1"
0o
0q
0s
b0 &
b0 3
b0 j
b0 m
0u
0y
0{
0}
b1010000 (
b1010000 4
b1010000 a
b1010000 +"
b0 %
b0 2
b0 Y
b0 i
b0 w
0!"
b0 :
b0 e
0$
0&"
b0 $"
0("
0L
0N
0P
b0 )
b0 5
b0 I
b0 S
0R
0A
0C
0E
b0 +
b0 8
b0 ?
0G
1.
#3
0.
#5
0%"
b0 ""
06
1Q
1M
b101 <
b101 J
b101 V
b101 \
1B
1F
b101 W
b101 `
b101 !
b101 /
b101 =
b101 T
b101 -"
bz ]
1^
0[
b10 U
1H
1#"
0b
b11010000100 9
b11010000100 f
b11010000100 g
1x
1z
1|
1~
0t
0)"
0h
b1111 v
b100 l
1$
1u
b101001 :
b101001 e
b101 &
b101 3
b101 j
b101 m
1q
b1001111 (
b1001111 4
b1001111 a
b1001111 +"
b1001111 #
b1001111 1
b1001111 k
b1001111 0"
b1 *
b1 7
b1 d
b1 1"
1,
#10
0,
#15
bz `
b101 ]
0^
1[
b0 U
0H
0#"
1b
b1000000001000 9
b1000000001000 f
b1000000001000 g
1)"
1h
b101000 :
b101000 e
0$
1N
b101 )
b101 5
b101 I
b101 S
1R
1,
#20
0,
#25
1O
1K
b1111 <
b1111 J
b1111 V
b1111 \
1@
1D
bz ]
b1111 W
b1111 !
b1111 /
b1111 =
b1111 T
b1111 -"
b1111 Z
0[
b10 U
1H
1#"
1X
0b
b11010000010 9
b11010000010 f
b11010000010 g
0x
0z
0|
1n
0p
1r
0)"
0h
b1 v
b1010 l
1$
1!"
1}
1{
b1111 %
b1111 2
b1111 Y
b1111 i
b1111 w
1y
b100001 :
b100001 e
b100 &
b100 3
b100 j
b100 m
0u
b111110100001 (
b111110100001 4
b111110100001 a
b111110100001 +"
b10100001 #
b10100001 1
b10100001 k
b10100001 0"
b10 *
b10 7
b10 d
b10 1"
1,
#30
0,
#35
b1111 ]
b1111 !
b1111 /
b1111 =
b1111 T
b1111 -"
bz Z
1[
b0 U
0H
0#"
0X
1b
b1000000001000 9
b1000000001000 f
b1000000001000 g
1)"
1h
b100000 :
b100000 e
0$
1L
b1111 )
b1111 5
b1111 I
b1111 S
1P
1,
#40
0,
#45
1%"
16
0Q
0O
0M
0K
1'"
b0 <
b0 J
b0 V
b0 \
b11 ""
1;
0@
0B
0D
bz ]
b10000 W
b1 !
b1 /
b1 =
b1 T
b1 -"
b1 Z
0[
b11 U
1H
1#"
1X
0b
b11011000010 9
b11011000010 f
b11011000010 g
0~
0n
1p
0r
0)"
0h
b0 v
b100 l
1$
0}
0{
b1 %
b1 2
b1 Y
b1 i
b1 w
0y
1s
0q
b1010001 :
b1010001 e
b1010 &
b1010 3
b1010 j
b1010 m
1o
b101000000 (
b101000000 4
b101000000 a
b101000000 +"
b1000000 #
b1000000 1
b1000000 k
b1000000 0"
b11 *
b11 7
b11 d
b11 1"
1,
#50
0,
#55
0F
b0 ]
b0 !
b0 /
b0 =
b0 T
b0 -"
bz Z
1[
b0 U
0H
0#"
0X
1b
b1000000001000 9
b1000000001000 f
b1000000001000 g
1%"
16
0Q
0'"
b0 <
b0 J
b0 V
b0 \
b1 ""
0;
1)"
1h
1"
1'
b0 W
b1010110 :
b1010110 e
0$
1&"
b11 $"
1("
0L
0N
0P
b0 )
b0 5
b0 I
b0 S
0R
1,
#60
0,
#65
bz ]
b0 Z
0[
b10 U
1H
1#"
1X
0b
b11010000010 9
b11010000010 f
b11010000010 g
1r
1t
0)"
0h
b111 l
1$
b0 %
b0 2
b0 Y
b0 i
b0 w
0!"
0s
1q
b100111 :
b100111 e
b100 &
b100 3
b100 j
b100 m
0o
b1110000 (
b1110000 4
b1110000 a
b1110000 +"
b1110000 #
b1110000 1
b1110000 k
b1110000 0"
b100 *
b100 7
b100 d
b100 1"
1,
#70
0,
#75
b0 ]
b0 !
b0 /
b0 =
b0 T
b0 -"
bz Z
1[
b0 U
0H
0#"
0X
1b
b1000000001000 9
b1000000001000 f
b1000000001000 g
1)"
1h
0'
b100010 :
b100010 e
0$
b1 $"
0("
1,
#80
0,
#85
1."
1,"
b1000000111000 9
b1000000111000 f
b1000000111000 g
1|
0p
0t
0)"
0h
b10 v
b10 l
1$
1u
b111011 :
b111011 e
b111 &
b111 3
b111 j
b111 m
1s
b100010 (
b100010 4
b100010 a
b100010 +"
b100010 #
b100010 1
b100010 k
b100010 0"
b101 *
b101 7
b101 d
b101 1"
1,
#90
0,
#95
0."
0,"
b1000000001000 9
b1000000001000 f
b1000000001000 g
0|
1~
1p
0r
b1 v
b100 l
1)"
1h
b1000001 (
b1000001 4
b1000001 a
b1000001 +"
b1000001 #
b1000001 1
b1000001 k
b1000001 0"
b110 *
b110 7
b110 d
b110 1"
b111010 :
b111010 e
0$
1,
#100
0,
#105
0%"
b0 ""
06
1Q
b1 <
b1 J
b1 V
b1 \
1F
bz ]
b1 W
b1 !
b1 /
b1 =
b1 T
b1 -"
b1 Z
0[
b10 U
1H
1#"
1X
0b
b11010000010 9
b11010000010 f
b11010000010 g
1r
1t
0)"
0h
b111 l
1$
b1 %
b1 2
b1 Y
b1 i
b1 w
1!"
0u
b100011 :
b100011 e
b100 &
b100 3
b100 j
b100 m
0s
b101110001 (
b101110001 4
b101110001 a
b101110001 +"
b1110001 #
b1110001 1
b1110001 k
b1110001 0"
b111 *
b111 7
b111 d
b111 1"
1,
#110
0,
#115
b1 ]
b1 !
b1 /
b1 =
b1 T
b1 -"
bz Z
1[
b0 U
0H
0#"
0X
1b
b1000000001000 9
b1000000001000 f
b1000000001000 g
1)"
1h
0"
b100000 :
b100000 e
0$
b0 $"
0&"
b1 )
b1 5
b1 I
b1 S
1R
1,
#120
0,
#125
1."
1,"
b1000000111000 9
b1000000111000 f
b1000000111000 g
1|
0~
0p
0t
0)"
0h
b10 v
b10 l
1$
1u
b111001 :
b111001 e
b111 &
b111 3
b111 j
b111 m
1s
b100100010 (
b100100010 4
b100100010 a
b100100010 +"
b100010 #
b100010 1
b100010 k
b100010 0"
b1000 *
b1000 7
b1000 d
b1000 1"
1,
#130
0,
#135
0."
0,"
b1000000001000 9
b1000000001000 f
b1000000001000 g
1p
0r
b100 l
1)"
1h
b101000010 (
b101000010 4
b101000010 a
b101000010 +"
b1000010 #
b1000010 1
b1000010 k
b1000010 0"
b1001 *
b1001 7
b1001 d
b1001 1"
b111000 :
b111000 e
0$
1,
#140
0,
#145
0%"
b0 ""
06
0Q
1O
b10 <
b10 J
b10 V
b10 \
1D
0F
bz ]
b10 W
b10 !
b10 /
b10 =
b10 T
b10 -"
b10 Z
0[
b10 U
1H
1#"
1X
0b
b11010000010 9
b11010000010 f
b11010000010 g
1r
1t
0)"
0h
b111 l
1$
0!"
b10 %
b10 2
b10 Y
b10 i
b10 w
1}
0u
b100001 :
b100001 e
b100 &
b100 3
b100 j
b100 m
0s
b1001110010 (
b1001110010 4
b1001110010 a
b1001110010 +"
b1110010 #
b1110010 1
b1110010 k
b1110010 0"
b1010 *
b1010 7
b1010 d
b1010 1"
1,
#150
0,
#155
b10 ]
b10 !
b10 /
b10 =
b10 T
b10 -"
bz Z
1[
b0 U
0H
0#"
0X
1b
b1000000001000 9
b1000000001000 f
b1000000001000 g
1)"
1h
b100000 :
b100000 e
0$
1P
b10 )
b10 5
b10 I
b10 S
0R
1,
#160
0,
#165
1."
1,"
b1000000111000 9
b1000000111000 f
b1000000111000 g
0|
0p
0r
0t
0)"
0h
b0 v
b0 l
1$
1u
b111001 :
b111001 e
b111 &
b111 3
b111 j
b111 m
1s
b1000000000 (
b1000000000 4
b1000000000 a
b1000000000 +"
b0 #
b0 1
b0 k
b0 0"
b1011 *
b1011 7
b1011 d
b1011 1"
1,
#170
0,
#175
0."
0,"
b1000000001000 9
b1000000001000 f
b1000000001000 g
1|
1p
1r
b10 v
b110 l
1)"
1h
b1001100010 (
b1001100010 4
b1001100010 a
b1001100010 +"
b1100010 #
b1100010 1
b1100010 k
b1100010 0"
b1100 *
b1100 7
b1100 d
b1100 1"
b111000 :
b111000 e
0$
1,
#180
0,
#185
0%"
b0 ""
06
0Q
1O
0M
0K
b10 <
b10 J
b10 V
b10 \
0@
0B
1D
0F
b10 W
b10 /"
b10 !
b10 /
b10 =
b10 T
b10 -"
bz ]
1,"
0[
b10 U
1H
1#"
b1011010100000 9
b1011010100000 f
b1011010100000 g
0|
0p
0r
0)"
0h
b0 v
b0 l
1$
b110001 :
b110001 e
b110 &
b110 3
b110 j
b110 m
0u
b1000000000 (
b1000000000 4
b1000000000 a
b1000000000 +"
b0 #
b0 1
b0 k
b0 0"
b1101 *
b1101 7
b1101 d
b1101 1"
1,
#190
0,
#195
b10 ]
0,"
1[
b0 U
0H
0#"
b1000000001000 9
b1000000001000 f
b1000000001000 g
0%"
b0 ""
06
0Q
1O
0M
0K
b10 <
b10 J
b10 V
b10 \
0@
0B
1D
0F
b10 W
b10 !
b10 /
b10 =
b10 T
b10 -"
1|
1p
b10 v
b100 l
bx /"
1)"
1h
b1001000010 (
b1001000010 4
b1001000010 a
b1001000010 +"
b1000010 #
b1000010 1
b1000010 k
b1000010 0"
b1110 *
b1110 7
b1110 d
b1110 1"
b110000 :
b110000 e
0$
1,
#200
0,
#205
bz ]
b10 Z
0[
b10 U
1H
1#"
1X
0b
b11010000010 9
b11010000010 f
b11010000010 g
1n
0p
1r
1t
0)"
0h
b1011 l
1$
b100001 :
b100001 e
b100 &
b100 3
b100 j
b100 m
0s
b1010110010 (
b1010110010 4
b1010110010 a
b1010110010 +"
b10110010 #
b10110010 1
b10110010 k
b10110010 0"
b1111 *
b1111 7
b1111 d
b1111 1"
1,
#210
0,
#215
b10 ]
b10 !
b10 /
b10 =
b10 T
b10 -"
bz Z
1[
b0 U
0H
0#"
0X
1b
b1000000001000 9
b1000000001000 f
b1000000001000 g
1)"
1h
b100000 :
b100000 e
0$
1,
#220
0,
#225
0%"
06
0Q
0K
0'"
b0 ""
0;
0O
1M
0@
0B
1D
0F
b100 <
b100 J
b100 V
b100 \
b10 /"
b10 !
b10 /
b10 =
b10 T
b10 -"
bz ]
b100 W
1,"
0[
b11 U
1H
1#"
b1011011100000 9
b1011011100000 f
b1011011100000 g
0|
0n
0r
0t
0)"
0h
b0 v
b0 l
1$
1u
1s
0q
b1011001 :
b1011001 e
b1011 &
b1011 3
b1011 j
b1011 m
1o
b1000000000 (
b1000000000 4
b1000000000 a
b1000000000 +"
b0 #
b0 1
b0 k
b0 0"
b10000 *
b10000 7
b10000 d
b10000 1"
1,
#230
0,
