Laboratorios/Lab03Digital1Gar19085/Tabla01POS/POS.v
//Universidad del Valle Digital 1
//Rodrigo José García Ambrosy Carne:19085
//Tabla 01 POS

//Hago el módulo
module POS();

//Variables de entrada y de salida
reg A, B, C;
wire w1, w2, w3, w4, w5, Y;

//compuertas

not N1(w1, A);
not N2(w2, B);
not N3(w3, C);

or O4(w4, A, B, w3);
or O5(w5, A, w2, w3);
or O6(w6, w1, w2, C);

and A7(Y, w4, w5, w6);

initial begin
    $display("A B C | Y");   //impresion de la tabla
    $display("---------"); 
    $monitor("%b %b %b | %b", A, B, C, Y);
    A = 0; B = 0; C = 0;
    #1 C = 1;
    #1 B = 1; C = 0;
    #1 C = 1;
    #1 A = 1; B = 0; C = 0;
    #1 C = 1;
    #1 B = 1; C = 0;
    #1 C = 1; 
    #1 $finish;
end

//código que habilita el GTKWave
    initial
        begin
            $dumpfile("POS_tb.vcd");
            $dumpvars(0, POS);
        end

endmodule

Laboratorios/Lab03Digital1Gar19085/Tabla01POS/POS_tb.vcd
$date
	Fri Jul 31 22:54:09 2020
$end
$version
	Icarus Verilog
$end
$timescale
	1ps
$end
$scope module POS $end
$var wire 1 ! Y $end
$var wire 1 " w1 $end
$var wire 1 # w2 $end
$var wire 1 $ w3 $end
$var wire 1 % w4 $end
$var wire 1 & w5 $end
$var wire 1 ' w6 $end
$var reg 1 ( A $end
$var reg 1 ) B $end
$var reg 1 * C $end
$upscope $end
$enddefinitions $end
#0
$dumpvars
0*
0)
0(
1'
1&
1%
1$
1#
1"
1!
$end
#1
0!
0%
0$
1*
#2
1!
1$
1%
0#
0*
1)
#3
0!
0&
0$
1*
#4
1!
1$
1#
1&
0"
0*
0)
1(
#5
0$
1*
#6
0!
0'
1$
0#
0*
1)
#7
1!
1'
0$
1*
