Laboratorios/Lab04Digital1Gar19085/Ejercicio4/ConfigT.v
//Universidad del Valle Digital 1
//Rodrigo José García Ambrosy Carne:19085
//Tablas Ejercicio 1
//Gate Level Modeling Tablas

//Inicio Tabla 1

module GateLvl_1(input wire A, B, C, output wire Y);
//Nots
    wire n1, n2, n3; 
//Salidas
    wire w1, w2, w3;

//Operadores
    not (n1, A);
    not (n2, B);
    not (n3, C);
    and (w1, n1, n3);
    and (w2, A, C);
    and (w3, A, n2);
    or  (Y, w1, w2, w3);
endmodule   

//Inicio Tabla 2

module GateLvl_2(input wire A, B, C, output wire Y);
//Nots
    wire n2;
//Salida solo es 'Y'

//Operadores
    not (n2, B);
    or  (Y, n2);
endmodule   

//Inicio Tabla 3

module GateLvl_3(input wire A, B, C, D, output wire Y);

//Nots
    wire n1, n2, n3, n4;
//Salidas
    wire w1, w2, w3, w4, w5, w6, w7, w8;

//Operadores
    not (n1, A);
    not (n2, B);
    not (n3, C);
    not (n4, D);
    and (w1, n1, n2, n3, n4);
    and (w2, A, B, n3, n4);
    and (w3, n1, B, n3, D);
    and (w4, A, n2, n3, D);
    and (w5, n1, n2, C, D);
    and (w6, A, B, C, D);
    and (w7, n1, B, C, n4);
    and (w8, A, n2, C, n4);
    or  (Y, w1, w2, w3, w4, w5, w6, w7, w8);
endmodule

//Inicio Tabla 4

module GateLvl_4(input wire A, B, C, D, output wire Y);

//Nots
    wire n3, n4;
//Salidas
    wire w1, w2, w3;

//Operadores
    not (n3, C);
    not (n4, D);
    and (w1, A, n3, n4);
    and (w2, A, B);
    and (w3, A, C);
    or  (Y, w1, w2, w3);
endmodule

//Inicio Configuracion Operadores Logicos Tablas Ejercicio 2

//Tabla 1
module Logic_Lvl_1(input wire A, B, C, D, output wire Y);

    assign Y = (~B & ~C & ~D) | (A & ~C) | (A & ~D) | (A & ~B);

endmodule

//Tabla 2
module Logic_Lvl_2(input wire A, B, C, output wire Y);

    assign Y = (~B) | (C);

endmodule

//Tabla 3
module Logic_Lvl_3(input wire A, B, C, D, output wire Y);

    assign Y = (~B & ~C & D) | (B) | (A & D);

endmodule

//Tabla 4
module Logic_Lvl_4(input wire A, B, C, output wire Y);

    assign Y = (~A & ~C) | (B);

endmodule

Laboratorios/Lab04Digital1Gar19085/Ejercicio4/ConfigT_tb.v
// Config de cada modulo en el Testbench();


//Inicio del module testbench

module testbench();

    reg p1, p2, p3; //Gate Lvl 1
    reg p4, p5, p6; //Gate Lvl 2
    reg p7, p8, p9, p10; //Gate Lvl 3
    reg p11, p12, p13, p14;//Gate Lvl 4
    reg o1, o2, o3, o4;   //Logic Lvl 1
    reg o5, o6, o7;   //Logic Lvl 2   
    reg o8, o9, o10, o11;     //Logic Lvl 3  
    reg o12, o13, o14;    //Logic Lvl 4
    wire pz1, pz2, pz3, pz4, pz5, pz6, pz7, pz8; //Salidas

//Tablas Ejercicio 1
    GateLvl_1      G1(p1, p2, p3, pz1); //Config Modulo
    GateLvl_2      G2(p4, p5, p6, pz3); //Config Modulo
    GateLvl_3      G3(p7, p8, p9, p10, pz5); //Config Modulo
    GateLvl_4      G4(p11, p12, p13, p14, pz7); //Config Modulo
//Tablas Ejercicio 2
    Logic_Lvl_1    L1(o1, o2, o3, o4, pz2); //Config Operador
    Logic_Lvl_2    L2(o5, o6, o7, pz4); //Config Operador
    Logic_Lvl_3    L3(o8, o9, o10, o11, pz6); //Config Operador
    Logic_Lvl_4    L4(o12, o13, o14, pz8); //Config Operador

//Inicio config GateLVL Ejercicio 1

    initial begin //Tabla 1
        $display("Tablas 1, 2, 3, 4, Ejercicio 1");
        $display("A B C | Y");
        $display("------|---");
        $monitor("%b %b %b | %b", p1, p2, p3, pz1);
           p1 = 0; p2 = 0; p3 = 0;
        #1 p1 = 0; p2 = 0; p3 = 1;
        #1 p1 = 0; p2 = 1; p3 = 0;
        #1 p1 = 0; p2 = 1; p3 = 1;
        #1 p1 = 1; p2 = 0; p3 = 0;
        #1 p1 = 1; p2 = 0; p3 = 1;
        #1 p1 = 1; p2 = 1; p3 = 0;
        #1 p1 = 1; p2 = 1; p3 = 1;
    end //Termina en 8

    initial begin //Tabla 2
        #9 
        $display("\n");
        $display("A B C | Y");
        $display("------|---");
        $monitor("%b %b %b | %b", p4, p5, p6, pz3);
           p4 = 0; p5 = 0; p6 = 0;
        #1 p4 = 0; p5 = 0; p6 = 1;
        #1 p4 = 0; p5 = 1; p6 = 0;
        #1 p4 = 0; p5 = 1; p6 = 1;
        #1 p4 = 1; p5 = 0; p6 = 0;
        #1 p4 = 1; p5 = 0; p6 = 1;
        #1 p4 = 1; p5 = 1; p6 = 0;
        #1 p4 = 1; p5 = 1; p6 = 1;
    end //Termina en 16

    initial begin //Tabla 3
        #17 
        $display("\n");
        $display("A B C  D | Y");
        $display("--------|---");
        $monitor("%b %b %b %b | %b", p7, p8, p9, p10, pz5);
           p7 = 0; p8 = 0; p9 = 0; p10 = 0;
        #1 p7 = 0; p8 = 0; p9 = 0; p10 = 1;
        #1 p7 = 0; p8 = 0; p9 = 1; p10 = 0;
        #1 p7 = 0; p8 = 0; p9 = 1; p10 = 1;
        #1 p7 = 0; p8 = 1; p9 = 0; p10 = 0;
        #1 p7 = 0; p8 = 1; p9 = 0; p10 = 1;
        #1 p7 = 0; p8 = 1; p9 = 1; p10 = 0;
        #1 p7 = 0; p8 = 1; p9 = 1; p10 = 1;
        #1 p7 = 1; p8 = 0; p9 = 0; p10 = 0;
        #1 p7 = 1; p8 = 0; p9 = 0; p10 = 1;
        #1 p7 = 1; p8 = 0; p9 = 1; p10 = 0;
        #1 p7 = 1; p8 = 0; p9 = 1; p10 = 1;
        #1 p7 = 1; p8 = 1; p9 = 0; p10 = 0;
        #1 p7 = 1; p8 = 1; p9 = 0; p10 = 1;
        #1 p7 = 1; p8 = 1; p9 = 1; p10 = 0;
        #1 p7 = 1; p8 = 1; p9 = 1; p10 = 1;
    end //Termina en 32

    initial begin //Tabla 4
        #33
        $display("\n");
        $display("A B C D | Y");
        $display("--------|---");
        $monitor("%b %b %b %b | %b", p11, p12, p13, p14, pz7);
           p11 = 0; p12 = 0; p13 = 0; p14 = 0;
        #1 p11 = 0; p12 = 0; p13 = 0; p14 = 1;
        #1 p11 = 0; p12 = 0; p13 = 1; p14 = 0;
        #1 p11 = 0; p12 = 0; p13 = 1; p14 = 1;
        #1 p11 = 0; p12 = 1; p13 = 0; p14 = 0;
        #1 p11 = 0; p12 = 1; p13 = 0; p14 = 1;
        #1 p11 = 0; p12 = 1; p13 = 1; p14 = 0;
        #1 p11 = 0; p12 = 1; p13 = 1; p14 = 1;
        #1 p11 = 1; p12 = 0; p13 = 0; p14 = 0;
        #1 p11 = 1; p12 = 0; p13 = 0; p14 = 1;
        #1 p11 = 1; p12 = 0; p13 = 1; p14 = 0;
        #1 p11 = 1; p12 = 0; p13 = 1; p14 = 1;
        #1 p11 = 1; p12 = 1; p13 = 0; p14 = 0;
        #1 p11 = 1; p12 = 1; p13 = 0; p14 = 1;
        #1 p11 = 1; p12 = 1; p13 = 1; p14 = 0;
        #1 p11 = 1; p12 = 1; p13 = 1; p14 = 1;
    end   //Termina en 48 

//Inicio config Operadores logicos Ejercicio 2
    initial begin //Tabla 1
        #49
        $display("\n");
        $display("Tablas 1, 2, 3, 4, Ejercicio 2");
        $display("A B C D | Y");
        $display("--------|---");
        $monitor("%b %b %b %b | %b", o1, o2, o3, o4, pz2);
           o1 = 0; o2 = 0; o3 = 0; o4 = 0;
        #1 o1 = 0; o2 = 0; o3 = 0; o4 = 1;
        #1 o1 = 0; o2 = 0; o3 = 1; o4 = 0;
        #1 o1 = 0; o2 = 0; o3 = 1; o4 = 1;
        #1 o1 = 0; o2 = 1; o3 = 0; o4 = 0;
        #1 o1 = 0; o2 = 1; o3 = 0; o4 = 1;
        #1 o1 = 0; o2 = 1; o3 = 1; o4 = 0;
        #1 o1 = 0; o2 = 1; o3 = 1; o4 = 1;
        #1 o1 = 1; o2 = 0; o3 = 0; o4 = 0;
        #1 o1 = 1; o2 = 0; o3 = 0; o4 = 1;
        #1 o1 = 1; o2 = 0; o3 = 1; o4 = 0;
        #1 o1 = 1; o2 = 0; o3 = 1; o4 = 1;
        #1 o1 = 1; o2 = 1; o3 = 0; o4 = 0;
        #1 o1 = 1; o2 = 1; o3 = 0; o4 = 1;
        #1 o1 = 1; o2 = 1; o3 = 1; o4 = 0;
        #1 o1 = 1; o2 = 1; o3 = 1; o4 = 1;
    end //Termina en 64

    initial begin //Tabla 2
       #65
        $display("\n");
        $display("A B C | Y");
        $display("------|---");
        $monitor("%b %b %b | %b", o5, o6, o7, pz4);
           o5 = 0; o6 = 0; o7 = 0;
        #1 o5 = 0; o6 = 0; o7 = 1;
        #1 o5 = 0; o6 = 1; o7 = 0;
        #1 o5 = 0; o6 = 1; o7 = 1;
        #1 o5 = 1; o6 = 0; o7 = 0;
        #1 o5 = 1; o6 = 0; o7 = 1;
        #1 o5 = 1; o6 = 1; o7 = 0;
        #1 o5 = 1; o6 = 1; o7 = 1;
    end //Termina en 72

    initial begin //Tabla 3
        #73
        $display("\n");
        $display("A B C D | Y");
        $display("--------|---");
        $monitor("%b %b %b %b | %b", o8, o9, o10, o11, pz6);
           o8 = 0; o9 = 0; o10 = 0; o11 = 0;
        #1 o8 = 0; o9 = 0; o10 = 0; o11 = 1;
        #1 o8 = 0; o9 = 0; o10 = 1; o11 = 0;
        #1 o8 = 0; o9 = 0; o10 = 1; o11 = 1;
        #1 o8 = 0; o9 = 1; o10 = 0; o11 = 0;
        #1 o8 = 0; o9 = 1; o10 = 0; o11 = 1;
        #1 o8 = 0; o9 = 1; o10 = 1; o11 = 0;
        #1 o8 = 0; o9 = 1; o10 = 1; o11 = 1;
        #1 o8 = 1; o9 = 0; o10 = 0; o11 = 0;
        #1 o8 = 1; o9 = 0; o10 = 0; o11 = 1;
        #1 o8 = 1; o9 = 0; o10 = 1; o11 = 0;
        #1 o8 = 1; o9 = 0; o10 = 1; o11 = 1;
        #1 o8 = 1; o9 = 1; o10 = 0; o11 = 0;
        #1 o8 = 1; o9 = 1; o10 = 0; o11 = 1;
        #1 o8 = 1; o9 = 1; o10 = 1; o11 = 0;
        #1 o8 = 1; o9 = 1; o10 = 1; o11 = 1;
    end //Termina en 88

    initial begin //Tabla 4
        #89
        $display("\n");
        $display("A B C | Y");
        $display("------|---");
        $monitor("%b %b %b | %b", o12, o13, o14, pz8);
           o12 = 0; o13 = 0; o14 = 0;
        #1 o12 = 0; o13 = 0; o14 = 1;
        #1 o12 = 0; o13 = 1; o14 = 0;
        #1 o12 = 0; o13 = 1; o14 = 1;
        #1 o12 = 1; o13 = 0; o14 = 0;
        #1 o12 = 1; o13 = 0; o14 = 1; 
        #1 o12 = 1; o13 = 1; o14 = 0; 
        #1 o12 = 1; o13 = 1; o14 = 1; 
    end   //Termina en 96

    initial
        #97 $finish;

    initial begin  
        $dumpfile("ConfigT_tb.vcd");
        $dumpvars(0, testbench);
    end 

endmodule

Laboratorios/Lab04Digital1Gar19085/Ejercicio4/ConfigT_tb.vcd
$date
	Sun Aug 09 18:47:44 2020
$end
$version
	Icarus Verilog
$end
$timescale
	1ps
$end
$scope module testbench $end
$var wire 1 ! pz8 $end
$var wire 1 " pz7 $end
$var wire 1 # pz6 $end
$var wire 1 $ pz5 $end
$var wire 1 % pz4 $end
$var wire 1 & pz3 $end
$var wire 1 ' pz2 $end
$var wire 1 ( pz1 $end
$var reg 1 ) o1 $end
$var reg 1 * o10 $end
$var reg 1 + o11 $end
$var reg 1 , o12 $end
$var reg 1 - o13 $end
$var reg 1 . o14 $end
$var reg 1 / o2 $end
$var reg 1 0 o3 $end
$var reg 1 1 o4 $end
$var reg 1 2 o5 $end
$var reg 1 3 o6 $end
$var reg 1 4 o7 $end
$var reg 1 5 o8 $end
$var reg 1 6 o9 $end
$var reg 1 7 p1 $end
$var reg 1 8 p10 $end
$var reg 1 9 p11 $end
$var reg 1 : p12 $end
$var reg 1 ; p13 $end
$var reg 1 < p14 $end
$var reg 1 = p2 $end
$var reg 1 > p3 $end
$var reg 1 ? p4 $end
$var reg 1 @ p5 $end
$var reg 1 A p6 $end
$var reg 1 B p7 $end
$var reg 1 C p8 $end
$var reg 1 D p9 $end
$scope module G1 $end
$var wire 1 7 A $end
$var wire 1 = B $end
$var wire 1 > C $end
$var wire 1 ( Y $end
$var wire 1 E n1 $end
$var wire 1 F n2 $end
$var wire 1 G n3 $end
$var wire 1 H w1 $end
$var wire 1 I w2 $end
$var wire 1 J w3 $end
$upscope $end
$scope module G2 $end
$var wire 1 ? A $end
$var wire 1 @ B $end
$var wire 1 A C $end
$var wire 1 & Y $end
$var wire 1 K n2 $end
$upscope $end
$scope module G3 $end
$var wire 1 B A $end
$var wire 1 C B $end
$var wire 1 D C $end
$var wire 1 8 D $end
$var wire 1 $ Y $end
$var wire 1 L n1 $end
$var wire 1 M n2 $end
$var wire 1 N n3 $end
$var wire 1 O n4 $end
$var wire 1 P w1 $end
$var wire 1 Q w2 $end
$var wire 1 R w3 $end
$var wire 1 S w4 $end
$var wire 1 T w5 $end
$var wire 1 U w6 $end
$var wire 1 V w7 $end
$var wire 1 W w8 $end
$upscope $end
$scope module G4 $end
$var wire 1 9 A $end
$var wire 1 : B $end
$var wire 1 ; C $end
$var wire 1 < D $end
$var wire 1 " Y $end
$var wire 1 X n3 $end
$var wire 1 Y n4 $end
$var wire 1 Z w1 $end
$var wire 1 [ w2 $end
$var wire 1 \ w3 $end
$upscope $end
$scope module L1 $end
$var wire 1 ) A $end
$var wire 1 / B $end
$var wire 1 0 C $end
$var wire 1 1 D $end
$var wire 1 ' Y $end
$upscope $end
$scope module L2 $end
$var wire 1 2 A $end
$var wire 1 3 B $end
$var wire 1 4 C $end
$var wire 1 % Y $end
$upscope $end
$scope module L3 $end
$var wire 1 5 A $end
$var wire 1 6 B $end
$var wire 1 * C $end
$var wire 1 + D $end
$var wire 1 # Y $end
$upscope $end
$scope module L4 $end
$var wire 1 , A $end
$var wire 1 - B $end
$var wire 1 . C $end
$var wire 1 ! Y $end
$upscope $end
$upscope $end
$enddefinitions $end
#0
$dumpvars
x\
x[
xZ
xY
xX
xW
xV
xU
xT
xS
xR
xQ
xP
xO
xN
xM
xL
xK
0J
0I
1H
1G
1F
1E
xD
xC
xB
xA
x@
x?
0>
0=
x<
x;
x:
x9
x8
07
x6
x5
x4
x3
x2
x1
x0
x/
x.
x-
x,
x+
x*
x)
1(
x'
x&
x%
x$
x#
x"
x!
$end
#1
0(
0H
0G
1>
#2
1(
1H
1G
0F
0>
1=
#3
0(
0H
0G
1>
#4
1(
1J
1G
1F
0E
0>
0=
17
#5
0G
1I
1>
#6
0(
0J
1G
0I
0F
0>
1=
#7
1(
0G
1I
1>
#9
1&
1K
0A
0@
0?
#10
1A
#11
0&
0K
0A
1@
#12
1A
#13
1&
1K
0A
0@
1?
#14
1A
#15
0&
0K
0A
1@
#16
1A
#17
1$
1P
1O
1N
0T
1M
0R
0V
1L
0Q
0S
0U
0W
08
0D
0C
0B
#18
0$
0P
0O
18
#19
1O
0N
08
1D
#20
1$
0O
1T
18
#21
0$
1O
1N
0T
0M
08
0D
1C
#22
1$
0O
1R
18
#23
1$
1V
1O
0R
0N
08
1D
#24
0$
0V
0O
18
#25
1O
1N
1M
0L
08
0D
0C
1B
#26
1$
0O
1S
18
#27
1$
1W
1O
0S
0N
08
1D
#28
0$
0W
0O
18
#29
1$
1Q
1O
1N
0M
08
0D
1C
#30
0$
0Q
0O
18
#31
1O
0N
08
1D
#32
1$
0O
1U
18
#33
0"
1Y
1X
0Z
0[
0\
0<
0;
0:
09
#34
0Y
1<
#35
1Y
0X
0<
1;
#36
0Y
1<
#37
1Y
1X
0<
0;
1:
#38
0Y
1<
#39
1Y
0X
0<
1;
#40
0Y
1<
#41
1"
1Z
1Y
1X
0<
0;
0:
19
#42
0"
0Z
0Y
1<
#43
1"
1Y
0X
1\
0<
1;
#44
0Y
1<
#45
1Z
1Y
1X
0\
1[
0<
0;
1:
#46
0Z
0Y
1<
#47
1Y
0X
1\
0<
1;
#48
0Y
1<
#49
1'
01
00
0/
0)
#50
0'
11
#51
01
10
#52
11
#53
01
00
1/
#54
11
#55
01
10
#56
11
#57
1'
01
00
0/
1)
#58
11
#59
01
10
#60
11
#61
1'
01
00
1/
#62
11
#63
01
10
#64
0'
11
#65
1%
04
03
02
#66
14
#67
0%
04
13
#68
1%
14
#69
04
03
12
#70
14
#71
0%
04
13
#72
1%
14
#73
0#
0+
0*
06
05
#74
1#
1+
#75
0#
0+
1*
#76
1+
#77
1#
0+
0*
16
#78
1+
#79
0+
1*
#80
1+
#81
0#
0+
0*
06
15
#82
1#
1+
#83
0#
0+
1*
#84
1#
1+
#85
0+
0*
16
#86
1+
#87
0+
1*
#88
1+
#89
1!
0.
0-
0,
#90
0!
1.
#91
1!
0.
1-
#92
1.
#93
0!
0.
0-
1,
#94
1.
#95
1!
0.
1-
#96
1.
