Laboratorios/Lab08Digital1Gar19085/Ejercicio03/ALU.v
//Universidad del Valle de Guatemala
//Lab08
//ALU de 4 bits
//Gar19085

module  ALU(A, B, SEL, OUT);
    input   [3:0] A, B;
    input   [2:0] SEL;
    output  [3:0] OUT;  
    reg [3:0] OUT;

    always @ (*)
    begin
        case (SEL)
            3'b000:    OUT = A & B;   
            3'b001:    OUT = A | B;
            3'b010:    OUT = A + B;
            3'b011:    OUT = A & ~B;
            3'b100:    OUT = A | ~B;
            3'b101:    OUT = A - B;
            3'b110:    OUT = (A < B) ? 1:0;
            default:    OUT = A & B;
        endcase
    end    
endmodule

Laboratorios/Lab08Digital1Gar19085/Ejercicio03/ALU_tb.v
//testbench



module  testbench();

reg [3:0] A,B;
reg [2:0] SEL;

wire [3:0] OUT;

    ALU Bf(A, B, SEL, OUT);

initial begin
        $display("\n");
        $display("Ejercicio 3");
        $display("A | B | SEL |  OUT");
        $monitor("%b |  %b  |   %b   |  %b", A, B, SEL, OUT);
        A = 0; B = 0; SEL = 0;
        #1 A = 1;
        #1 B = 1;
        #1 SEL = 0;
        #1 SEL = 1;
        #1 SEL = 2;
        #1 SEL = 3;
        #1 SEL = 4;
        #1 SEL = 5;
        #1 A = 5; SEL = 5;
        #1 SEL = 6;
        #1 B = 6;
end

   initial 
        #20 $finish;

        initial begin
            $dumpfile("ALU_tb.vcd");
            $dumpvars(0, testbench);
        end


endmodule

Laboratorios/Lab08Digital1Gar19085/Ejercicio03/ALU_tb.vcd
$date
	Sat Oct 24 17:07:43 2020
$end
$version
	Icarus Verilog
$end
$timescale
	1ps
$end
$scope module testbench $end
$var wire 4 ! OUT [3:0] $end
$var reg 4 " A [3:0] $end
$var reg 4 # B [3:0] $end
$var reg 3 $ SEL [2:0] $end
$scope module Bf $end
$var wire 4 % A [3:0] $end
$var wire 4 & B [3:0] $end
$var wire 3 ' SEL [2:0] $end
$var reg 4 ( OUT [3:0] $end
$upscope $end
$upscope $end
$enddefinitions $end
#0
$dumpvars
b0 (
b0 '
b0 &
b0 %
b0 $
b0 #
b0 "
b0 !
$end
#1
b1 "
b1 %
#2
b1 !
b1 (
b1 #
b1 &
#4
b1 $
b1 '
#5
b10 !
b10 (
b10 $
b10 '
#6
b0 !
b0 (
b11 $
b11 '
#7
b1111 !
b1111 (
b100 $
b100 '
#8
b0 !
b0 (
b101 $
b101 '
#9
b100 !
b100 (
b101 "
b101 %
#10
b0 !
b0 (
b110 $
b110 '
#11
b1 !
b1 (
b110 #
b110 &
