Laboratorios/Lab09Digital1Gar19085/Ejercicio03/FFJK.v

module FFD1 (input CLK, RST, ENABLE, D,
            output reg Q);
        always @ (posedge CLK or posedge RST)begin
            if (RST) begin
                Q <= 1'b0;
            end
            else if (ENABLE) begin
                Q <= D;
            end
        end   
endmodule


module FFJK(input CLK, RST, ENABLE, J, K,
            output wire Q);
        wire A1, A2, NK, NS0, S0, SF0;
        
        not(NK, K);
        not(NS0, S0);
        and(A1, NS0, J);
        and(A2, S0, NK);
        or(SF0, A1, A2);
   
        assign Q = SF0;  
        
        FFD1 BF(CLK, RST, ENABLE, SF0, S0);

endmodule

Laboratorios/Lab09Digital1Gar19085/Ejercicio03/FFJK_tb.v



module Testbench();



reg CLK, RST, ENABLE, J, K;
wire Q;


FFJK Ju88(CLK, RST, ENABLE, J, K, Q);


        always 
            begin 
                CLK <= 0; RST <= 0; #1 CLK <= 1; #1;
            end

            
    initial begin
        $display("\n");
        $display("FLIP-FLOP JK");
        $display("CLK | RST | ENABLE | J  | K   | Q");
        $monitor("%b  | %b  |    %b  | %b |  %b | %b",
                CLK,RST, ENABLE, J, K, Q);
        CLK = 0; RST = 0; ENABLE = 0; J = 0; K = 0;        
     #1  RST = 1;
     #1  RST = 0;
     #2  ENABLE = 1;  
     #2 J = 1;
     #2 K = 1;
     #6 J = 0;
     #6 K = 0;
     #2 J = 1;
    end

   always
    #1  CLK = ~CLK;
  
   initial 
        #25 $finish;

        initial begin
            $dumpfile("FFJK_tb.vcd");
            $dumpvars(0, Testbench);
        end

        endmodule

Laboratorios/Lab09Digital1Gar19085/Ejercicio03/FFJK_tb.vcd
$date
	Fri Oct 30 19:29:57 2020
$end
$version
	Icarus Verilog
$end
$timescale
	1ps
$end
$scope module Testbench $end
$var wire 1 ! Q $end
$var reg 1 " CLK $end
$var reg 1 # ENABLE $end
$var reg 1 $ J $end
$var reg 1 % K $end
$var reg 1 & RST $end
$scope module Ju88 $end
$var wire 1 ' A1 $end
$var wire 1 ( A2 $end
$var wire 1 " CLK $end
$var wire 1 # ENABLE $end
$var wire 1 $ J $end
$var wire 1 % K $end
$var wire 1 ) NK $end
$var wire 1 * NS0 $end
$var wire 1 ! Q $end
$var wire 1 & RST $end
$var wire 1 + SF0 $end
$var wire 1 , S0 $end
$scope module BF $end
$var wire 1 " CLK $end
$var wire 1 + D $end
$var wire 1 # ENABLE $end
$var wire 1 & RST $end
$var reg 1 , Q $end
$upscope $end
$upscope $end
$upscope $end
$enddefinitions $end
#0
$dumpvars
x,
x+
x*
1)
x(
0'
0&
0%
0$
0#
0"
x!
$end
#1
0!
0+
0(
1*
0,
1"
1&
#2
0"
0&
#3
1"
#4
0"
1#
#5
1"
#6
1!
1+
1'
0"
1$
#7
0'
1(
0*
1,
1"
#8
0!
0+
0(
0)
0"
1%
#9
1!
1+
1'
1*
0,
1"
#10
0"
#11
0!
0+
0'
0*
1,
1"
#12
0"
#13
1!
1+
1'
1*
0,
1"
#14
0!
0+
0'
0"
0$
#15
1"
#16
0"
#17
1"
#18
0"
#19
1"
#20
1)
0"
0%
#21
1"
#22
1!
1+
1'
0"
1$
#23
0'
1(
0*
1,
1"
